{"file":"skill_chibang_10_xiao.png","frames":{
"skill_chibang_09_01":{"x":2035,"y":0,"w":5,"h":5,"offX":0,"offY":0,"sourceW":460,"sourceH":340},
"skill_chibang_09_02":{"x":1745,"y":466,"w":194,"h":120,"offX":133,"offY":104,"sourceW":460,"sourceH":340},
"skill_chibang_09_03":{"x":1745,"y":332,"w":218,"h":132,"offX":121,"offY":100,"sourceW":460,"sourceH":340},
"skill_chibang_09_04":{"x":1746,"y":175,"w":253,"h":155,"offX":102,"offY":90,"sourceW":460,"sourceH":340},
"skill_chibang_09_05":{"x":1746,"y":0,"w":287,"h":173,"offX":86,"offY":86,"sourceW":460,"sourceH":340},
"skill_chibang_09_06":{"x":1347,"y":481,"w":312,"h":188,"offX":74,"offY":81,"sourceW":460,"sourceH":340},
"skill_chibang_09_07":{"x":683,"y":470,"w":331,"h":200,"offX":64,"offY":75,"sourceW":460,"sourceH":340},
"skill_chibang_09_08":{"x":0,"y":250,"w":339,"h":208,"offX":60,"offY":71,"sourceW":460,"sourceH":340},
"skill_chibang_09_09":{"x":701,"y":248,"w":347,"h":220,"offX":56,"offY":61,"sourceW":460,"sourceH":340},
"skill_chibang_09_10":{"x":351,"y":0,"w":348,"h":248,"offX":56,"offY":46,"sourceW":460,"sourceH":340},
"skill_chibang_09_11":{"x":0,"y":0,"w":349,"h":248,"offX":55,"offY":46,"sourceW":460,"sourceH":340},
"skill_chibang_09_12":{"x":701,"y":0,"w":347,"h":246,"offX":56,"offY":46,"sourceW":460,"sourceH":340},
"skill_chibang_09_13":{"x":1050,"y":0,"w":347,"h":243,"offX":56,"offY":47,"sourceW":460,"sourceH":340},
"skill_chibang_09_14":{"x":1399,"y":0,"w":345,"h":242,"offX":57,"offY":47,"sourceW":460,"sourceH":340},
"skill_chibang_09_15":{"x":1399,"y":244,"w":344,"h":235,"offX":58,"offY":50,"sourceW":460,"sourceH":340},
"skill_chibang_09_16":{"x":1050,"y":245,"w":343,"h":225,"offX":58,"offY":55,"sourceW":460,"sourceH":340},
"skill_chibang_09_17":{"x":341,"y":250,"w":340,"h":205,"offX":60,"offY":63,"sourceW":460,"sourceH":340},
"skill_chibang_09_18":{"x":341,"y":457,"w":340,"h":205,"offX":60,"offY":63,"sourceW":460,"sourceH":340},
"skill_chibang_09_19":{"x":0,"y":460,"w":336,"h":201,"offX":62,"offY":65,"sourceW":460,"sourceH":340},
"skill_chibang_09_20":{"x":1016,"y":472,"w":329,"h":194,"offX":65,"offY":69,"sourceW":460,"sourceH":340}}}