{
	"gdTopLevelAttrs":{
			"1":{"id":1,"icon":"UI_CQ_skill_shengmingzh1","max":50,"type":1},
			"2":{"id":2,"icon":"UI_CQ_skill_mofazhi","max":50,"type":2},
			"3":{"id":3,"icon":"UI_CQ_skill_zbdiaolv","max":50,"type":37},
			"4":{"id":4,"icon":"UI_CQ_skill_jpbaolv","max":50,"type":38},
			"5":{"id":5,"icon":"UI_CQ_skill_zhimingyiji","max":50,"type":62},
			"6":{"id":6,"icon":"UI_CQ_skill_zhimingshanghai","max":50,"type":64},
			"7":{"id":7,"icon":"UI_CQ_skill_shanghaifantanjilv","max":50,"type":66},
			"8":{"id":8,"icon":"UI_CQ_skill_fantanzhuanhualv","max":50,"type":68},
			"9":{"id":9,"icon":"UI_CQ_skill_zhuoshaokangxing","max":50,"type":52},
			"10":{"id":10,"icon":"UI_CQ_skill_bingdongkangxing","max":50,"type":48},
			"11":{"id":11,"icon":"UI_CQ_skill_leidiankangxing","max":50,"type":50},
			"12":{"id":12,"icon":"UI_CQ_skill_dukang","max":50,"type":54},
			"13":{"id":13,"icon":"UI_CQ_skill_wulimianyi","max":50,"type":34},
			"14":{"id":14,"icon":"UI_CQ_skill_mofa mianshang","max":50,"type":35},
			"15":{"id":15,"icon":"UI_CQ_skill_hushifangyu","max":50,"type":20},
			"16":{"id":16,"icon":"UI_CQ_skill_shanghaifantan","max":50,"type":63}
		},
	"gdTopLevelGroups":{
			"1":{"1":1,"2":2,"3":3,"4":4},
			"2":{"1":5,"2":6,"3":7,"4":8},
			"3":{"1":9,"2":10,"3":11,"4":12},
			"4":{"1":13,"2":14,"3":15,"4":16}
		},
	"gdTopLevelUpAttrs":{
			"1":{
					"1":{
							"attrs":{"1":100,"2":100,"3":100},
							"force":100,
							"level":1
						},
					"2":{
							"attrs":{"1":200,"2":200,"3":200},
							"force":200,
							"level":2
						},
					"3":{
							"attrs":{"1":300,"2":300,"3":300},
							"force":300,
							"level":3
						},
					"4":{
							"attrs":{"1":400,"2":400,"3":400},
							"force":400,
							"level":4
						},
					"5":{
							"attrs":{"1":500,"2":500,"3":500},
							"force":500,
							"level":5
						},
					"6":{
							"attrs":{"1":600,"2":600,"3":600},
							"force":600,
							"level":6
						},
					"7":{
							"attrs":{"1":700,"2":700,"3":700},
							"force":700,
							"level":7
						},
					"8":{
							"attrs":{"1":800,"2":800,"3":800},
							"force":800,
							"level":8
						},
					"9":{
							"attrs":{"1":900,"2":900,"3":900},
							"force":900,
							"level":9
						},
					"10":{
							"attrs":{"1":1000,"2":1000,"3":1000},
							"force":1000,
							"level":10
						},
					"11":{
							"attrs":{"1":1100,"2":1100,"3":1100},
							"force":1100,
							"level":11
						},
					"12":{
							"attrs":{"1":1200,"2":1200,"3":1200},
							"force":1200,
							"level":12
						},
					"13":{
							"attrs":{"1":1300,"2":1300,"3":1300},
							"force":1300,
							"level":13
						},
					"14":{
							"attrs":{"1":1400,"2":1400,"3":1400},
							"force":1400,
							"level":14
						},
					"15":{
							"attrs":{"1":1500,"2":1500,"3":1500},
							"force":1500,
							"level":15
						},
					"16":{
							"attrs":{"1":1600,"2":1600,"3":1600},
							"force":1600,
							"level":16
						},
					"17":{
							"attrs":{"1":1700,"2":1700,"3":1700},
							"force":1700,
							"level":17
						},
					"18":{
							"attrs":{"1":1800,"2":1800,"3":1800},
							"force":1800,
							"level":18
						},
					"19":{
							"attrs":{"1":1900,"2":1900,"3":1900},
							"force":1900,
							"level":19
						},
					"20":{
							"attrs":{"1":2000,"2":2000,"3":2000},
							"force":2000,
							"level":20
						},
					"21":{
							"attrs":{"1":2100,"2":2100,"3":2100},
							"force":2100,
							"level":21
						},
					"22":{
							"attrs":{"1":2200,"2":2200,"3":2200},
							"force":2200,
							"level":22
						},
					"23":{
							"attrs":{"1":2300,"2":2300,"3":2300},
							"force":2300,
							"level":23
						},
					"24":{
							"attrs":{"1":2400,"2":2400,"3":2400},
							"force":2400,
							"level":24
						},
					"25":{
							"attrs":{"1":2500,"2":2500,"3":2500},
							"force":2500,
							"level":25
						},
					"26":{
							"attrs":{"1":2600,"2":2600,"3":2600},
							"force":2600,
							"level":26
						},
					"27":{
							"attrs":{"1":2700,"2":2700,"3":2700},
							"force":2700,
							"level":27
						},
					"28":{
							"attrs":{"1":2800,"2":2800,"3":2800},
							"force":2800,
							"level":28
						},
					"29":{
							"attrs":{"1":2900,"2":2900,"3":2900},
							"force":2900,
							"level":29
						},
					"30":{
							"attrs":{"1":3000,"2":3000,"3":3000},
							"force":3000,
							"level":30
						},
					"31":{
							"attrs":{"1":3100,"2":3100,"3":3100},
							"force":3100,
							"level":31
						},
					"32":{
							"attrs":{"1":3200,"2":3200,"3":3200},
							"force":3200,
							"level":32
						},
					"33":{
							"attrs":{"1":3300,"2":3300,"3":3300},
							"force":3300,
							"level":33
						},
					"34":{
							"attrs":{"1":3400,"2":3400,"3":3400},
							"force":3400,
							"level":34
						},
					"35":{
							"attrs":{"1":3500,"2":3500,"3":3500},
							"force":3500,
							"level":35
						},
					"36":{
							"attrs":{"1":3600,"2":3600,"3":3600},
							"force":3600,
							"level":36
						},
					"37":{
							"attrs":{"1":3700,"2":3700,"3":3700},
							"force":3700,
							"level":37
						},
					"38":{
							"attrs":{"1":3800,"2":3800,"3":3800},
							"force":3800,
							"level":38
						},
					"39":{
							"attrs":{"1":3900,"2":3900,"3":3900},
							"force":3900,
							"level":39
						},
					"40":{
							"attrs":{"1":4000,"2":4000,"3":4000},
							"force":4000,
							"level":40
						},
					"41":{
							"attrs":{"1":4100,"2":4100,"3":4100},
							"force":4100,
							"level":41
						},
					"42":{
							"attrs":{"1":4200,"2":4200,"3":4200},
							"force":4200,
							"level":42
						},
					"43":{
							"attrs":{"1":4300,"2":4300,"3":4300},
							"force":4300,
							"level":43
						},
					"44":{
							"attrs":{"1":4400,"2":4400,"3":4400},
							"force":4400,
							"level":44
						},
					"45":{
							"attrs":{"1":4500,"2":4500,"3":4500},
							"force":4500,
							"level":45
						},
					"46":{
							"attrs":{"1":4600,"2":4600,"3":4600},
							"force":4600,
							"level":46
						},
					"47":{
							"attrs":{"1":4700,"2":4700,"3":4700},
							"force":4700,
							"level":47
						},
					"48":{
							"attrs":{"1":4800,"2":4800,"3":4800},
							"force":4800,
							"level":48
						},
					"49":{
							"attrs":{"1":4900,"2":4900,"3":4900},
							"force":4900,
							"level":49
						},
					"50":{
							"attrs":{"1":5000,"2":5000,"3":5000},
							"force":5000,
							"level":50
						}
				},
			"2":{
					"1":{
							"attrs":{"1":100,"2":100,"3":100},
							"force":100,
							"level":1
						},
					"2":{
							"attrs":{"1":200,"2":200,"3":200},
							"force":200,
							"level":2
						},
					"3":{
							"attrs":{"1":300,"2":300,"3":300},
							"force":300,
							"level":3
						},
					"4":{
							"attrs":{"1":400,"2":400,"3":400},
							"force":400,
							"level":4
						},
					"5":{
							"attrs":{"1":500,"2":500,"3":500},
							"force":500,
							"level":5
						},
					"6":{
							"attrs":{"1":600,"2":600,"3":600},
							"force":600,
							"level":6
						},
					"7":{
							"attrs":{"1":700,"2":700,"3":700},
							"force":700,
							"level":7
						},
					"8":{
							"attrs":{"1":800,"2":800,"3":800},
							"force":800,
							"level":8
						},
					"9":{
							"attrs":{"1":900,"2":900,"3":900},
							"force":900,
							"level":9
						},
					"10":{
							"attrs":{"1":1000,"2":1000,"3":1000},
							"force":1000,
							"level":10
						},
					"11":{
							"attrs":{"1":1100,"2":1100,"3":1100},
							"force":1100,
							"level":11
						},
					"12":{
							"attrs":{"1":1200,"2":1200,"3":1200},
							"force":1200,
							"level":12
						},
					"13":{
							"attrs":{"1":1300,"2":1300,"3":1300},
							"force":1300,
							"level":13
						},
					"14":{
							"attrs":{"1":1400,"2":1400,"3":1400},
							"force":1400,
							"level":14
						},
					"15":{
							"attrs":{"1":1500,"2":1500,"3":1500},
							"force":1500,
							"level":15
						},
					"16":{
							"attrs":{"1":1600,"2":1600,"3":1600},
							"force":1600,
							"level":16
						},
					"17":{
							"attrs":{"1":1700,"2":1700,"3":1700},
							"force":1700,
							"level":17
						},
					"18":{
							"attrs":{"1":1800,"2":1800,"3":1800},
							"force":1800,
							"level":18
						},
					"19":{
							"attrs":{"1":1900,"2":1900,"3":1900},
							"force":1900,
							"level":19
						},
					"20":{
							"attrs":{"1":2000,"2":2000,"3":2000},
							"force":2000,
							"level":20
						},
					"21":{
							"attrs":{"1":2100,"2":2100,"3":2100},
							"force":2100,
							"level":21
						},
					"22":{
							"attrs":{"1":2200,"2":2200,"3":2200},
							"force":2200,
							"level":22
						},
					"23":{
							"attrs":{"1":2300,"2":2300,"3":2300},
							"force":2300,
							"level":23
						},
					"24":{
							"attrs":{"1":2400,"2":2400,"3":2400},
							"force":2400,
							"level":24
						},
					"25":{
							"attrs":{"1":2500,"2":2500,"3":2500},
							"force":2500,
							"level":25
						},
					"26":{
							"attrs":{"1":2600,"2":2600,"3":2600},
							"force":2600,
							"level":26
						},
					"27":{
							"attrs":{"1":2700,"2":2700,"3":2700},
							"force":2700,
							"level":27
						},
					"28":{
							"attrs":{"1":2800,"2":2800,"3":2800},
							"force":2800,
							"level":28
						},
					"29":{
							"attrs":{"1":2900,"2":2900,"3":2900},
							"force":2900,
							"level":29
						},
					"30":{
							"attrs":{"1":3000,"2":3000,"3":3000},
							"force":3000,
							"level":30
						},
					"31":{
							"attrs":{"1":3100,"2":3100,"3":3100},
							"force":3100,
							"level":31
						},
					"32":{
							"attrs":{"1":3200,"2":3200,"3":3200},
							"force":3200,
							"level":32
						},
					"33":{
							"attrs":{"1":3300,"2":3300,"3":3300},
							"force":3300,
							"level":33
						},
					"34":{
							"attrs":{"1":3400,"2":3400,"3":3400},
							"force":3400,
							"level":34
						},
					"35":{
							"attrs":{"1":3500,"2":3500,"3":3500},
							"force":3500,
							"level":35
						},
					"36":{
							"attrs":{"1":3600,"2":3600,"3":3600},
							"force":3600,
							"level":36
						},
					"37":{
							"attrs":{"1":3700,"2":3700,"3":3700},
							"force":3700,
							"level":37
						},
					"38":{
							"attrs":{"1":3800,"2":3800,"3":3800},
							"force":3800,
							"level":38
						},
					"39":{
							"attrs":{"1":3900,"2":3900,"3":3900},
							"force":3900,
							"level":39
						},
					"40":{
							"attrs":{"1":4000,"2":4000,"3":4000},
							"force":4000,
							"level":40
						},
					"41":{
							"attrs":{"1":4100,"2":4100,"3":4100},
							"force":4100,
							"level":41
						},
					"42":{
							"attrs":{"1":4200,"2":4200,"3":4200},
							"force":4200,
							"level":42
						},
					"43":{
							"attrs":{"1":4300,"2":4300,"3":4300},
							"force":4300,
							"level":43
						},
					"44":{
							"attrs":{"1":4400,"2":4400,"3":4400},
							"force":4400,
							"level":44
						},
					"45":{
							"attrs":{"1":4500,"2":4500,"3":4500},
							"force":4500,
							"level":45
						},
					"46":{
							"attrs":{"1":4600,"2":4600,"3":4600},
							"force":4600,
							"level":46
						},
					"47":{
							"attrs":{"1":4700,"2":4700,"3":4700},
							"force":4700,
							"level":47
						},
					"48":{
							"attrs":{"1":4800,"2":4800,"3":4800},
							"force":4800,
							"level":48
						},
					"49":{
							"attrs":{"1":4900,"2":4900,"3":4900},
							"force":4900,
							"level":49
						},
					"50":{
							"attrs":{"1":5000,"2":5000,"3":5000},
							"force":5000,
							"level":50
						}
				},
			"3":{
					"1":{
							"attrs":{"1":100,"2":100,"3":100},
							"force":100,
							"level":1
						},
					"2":{
							"attrs":{"1":200,"2":200,"3":200},
							"force":200,
							"level":2
						},
					"3":{
							"attrs":{"1":300,"2":300,"3":300},
							"force":300,
							"level":3
						},
					"4":{
							"attrs":{"1":400,"2":400,"3":400},
							"force":400,
							"level":4
						},
					"5":{
							"attrs":{"1":500,"2":500,"3":500},
							"force":500,
							"level":5
						},
					"6":{
							"attrs":{"1":600,"2":600,"3":600},
							"force":600,
							"level":6
						},
					"7":{
							"attrs":{"1":700,"2":700,"3":700},
							"force":700,
							"level":7
						},
					"8":{
							"attrs":{"1":800,"2":800,"3":800},
							"force":800,
							"level":8
						},
					"9":{
							"attrs":{"1":900,"2":900,"3":900},
							"force":900,
							"level":9
						},
					"10":{
							"attrs":{"1":1000,"2":1000,"3":1000},
							"force":1000,
							"level":10
						},
					"11":{
							"attrs":{"1":1100,"2":1100,"3":1100},
							"force":1100,
							"level":11
						},
					"12":{
							"attrs":{"1":1200,"2":1200,"3":1200},
							"force":1200,
							"level":12
						},
					"13":{
							"attrs":{"1":1300,"2":1300,"3":1300},
							"force":1300,
							"level":13
						},
					"14":{
							"attrs":{"1":1400,"2":1400,"3":1400},
							"force":1400,
							"level":14
						},
					"15":{
							"attrs":{"1":1500,"2":1500,"3":1500},
							"force":1500,
							"level":15
						},
					"16":{
							"attrs":{"1":1600,"2":1600,"3":1600},
							"force":1600,
							"level":16
						},
					"17":{
							"attrs":{"1":1700,"2":1700,"3":1700},
							"force":1700,
							"level":17
						},
					"18":{
							"attrs":{"1":1800,"2":1800,"3":1800},
							"force":1800,
							"level":18
						},
					"19":{
							"attrs":{"1":1900,"2":1900,"3":1900},
							"force":1900,
							"level":19
						},
					"20":{
							"attrs":{"1":2000,"2":2000,"3":2000},
							"force":2000,
							"level":20
						},
					"21":{
							"attrs":{"1":2100,"2":2100,"3":2100},
							"force":2100,
							"level":21
						},
					"22":{
							"attrs":{"1":2200,"2":2200,"3":2200},
							"force":2200,
							"level":22
						},
					"23":{
							"attrs":{"1":2300,"2":2300,"3":2300},
							"force":2300,
							"level":23
						},
					"24":{
							"attrs":{"1":2400,"2":2400,"3":2400},
							"force":2400,
							"level":24
						},
					"25":{
							"attrs":{"1":2500,"2":2500,"3":2500},
							"force":2500,
							"level":25
						},
					"26":{
							"attrs":{"1":2600,"2":2600,"3":2600},
							"force":2600,
							"level":26
						},
					"27":{
							"attrs":{"1":2700,"2":2700,"3":2700},
							"force":2700,
							"level":27
						},
					"28":{
							"attrs":{"1":2800,"2":2800,"3":2800},
							"force":2800,
							"level":28
						},
					"29":{
							"attrs":{"1":2900,"2":2900,"3":2900},
							"force":2900,
							"level":29
						},
					"30":{
							"attrs":{"1":3000,"2":3000,"3":3000},
							"force":3000,
							"level":30
						},
					"31":{
							"attrs":{"1":3100,"2":3100,"3":3100},
							"force":3100,
							"level":31
						},
					"32":{
							"attrs":{"1":3200,"2":3200,"3":3200},
							"force":3200,
							"level":32
						},
					"33":{
							"attrs":{"1":3300,"2":3300,"3":3300},
							"force":3300,
							"level":33
						},
					"34":{
							"attrs":{"1":3400,"2":3400,"3":3400},
							"force":3400,
							"level":34
						},
					"35":{
							"attrs":{"1":3500,"2":3500,"3":3500},
							"force":3500,
							"level":35
						},
					"36":{
							"attrs":{"1":3600,"2":3600,"3":3600},
							"force":3600,
							"level":36
						},
					"37":{
							"attrs":{"1":3700,"2":3700,"3":3700},
							"force":3700,
							"level":37
						},
					"38":{
							"attrs":{"1":3800,"2":3800,"3":3800},
							"force":3800,
							"level":38
						},
					"39":{
							"attrs":{"1":3900,"2":3900,"3":3900},
							"force":3900,
							"level":39
						},
					"40":{
							"attrs":{"1":4000,"2":4000,"3":4000},
							"force":4000,
							"level":40
						},
					"41":{
							"attrs":{"1":4100,"2":4100,"3":4100},
							"force":4100,
							"level":41
						},
					"42":{
							"attrs":{"1":4200,"2":4200,"3":4200},
							"force":4200,
							"level":42
						},
					"43":{
							"attrs":{"1":4300,"2":4300,"3":4300},
							"force":4300,
							"level":43
						},
					"44":{
							"attrs":{"1":4400,"2":4400,"3":4400},
							"force":4400,
							"level":44
						},
					"45":{
							"attrs":{"1":4500,"2":4500,"3":4500},
							"force":4500,
							"level":45
						},
					"46":{
							"attrs":{"1":4600,"2":4600,"3":4600},
							"force":4600,
							"level":46
						},
					"47":{
							"attrs":{"1":4700,"2":4700,"3":4700},
							"force":4700,
							"level":47
						},
					"48":{
							"attrs":{"1":4800,"2":4800,"3":4800},
							"force":4800,
							"level":48
						},
					"49":{
							"attrs":{"1":4900,"2":4900,"3":4900},
							"force":4900,
							"level":49
						},
					"50":{
							"attrs":{"1":5000,"2":5000,"3":5000},
							"force":5000,
							"level":50
						}
				},
			"4":{
					"1":{
							"attrs":{"1":100,"2":100,"3":100},
							"force":100,
							"level":1
						},
					"2":{
							"attrs":{"1":200,"2":200,"3":200},
							"force":200,
							"level":2
						},
					"3":{
							"attrs":{"1":300,"2":300,"3":300},
							"force":300,
							"level":3
						},
					"4":{
							"attrs":{"1":400,"2":400,"3":400},
							"force":400,
							"level":4
						},
					"5":{
							"attrs":{"1":500,"2":500,"3":500},
							"force":500,
							"level":5
						},
					"6":{
							"attrs":{"1":600,"2":600,"3":600},
							"force":600,
							"level":6
						},
					"7":{
							"attrs":{"1":700,"2":700,"3":700},
							"force":700,
							"level":7
						},
					"8":{
							"attrs":{"1":800,"2":800,"3":800},
							"force":800,
							"level":8
						},
					"9":{
							"attrs":{"1":900,"2":900,"3":900},
							"force":900,
							"level":9
						},
					"10":{
							"attrs":{"1":1000,"2":1000,"3":1000},
							"force":1000,
							"level":10
						},
					"11":{
							"attrs":{"1":1100,"2":1100,"3":1100},
							"force":1100,
							"level":11
						},
					"12":{
							"attrs":{"1":1200,"2":1200,"3":1200},
							"force":1200,
							"level":12
						},
					"13":{
							"attrs":{"1":1300,"2":1300,"3":1300},
							"force":1300,
							"level":13
						},
					"14":{
							"attrs":{"1":1400,"2":1400,"3":1400},
							"force":1400,
							"level":14
						},
					"15":{
							"attrs":{"1":1500,"2":1500,"3":1500},
							"force":1500,
							"level":15
						},
					"16":{
							"attrs":{"1":1600,"2":1600,"3":1600},
							"force":1600,
							"level":16
						},
					"17":{
							"attrs":{"1":1700,"2":1700,"3":1700},
							"force":1700,
							"level":17
						},
					"18":{
							"attrs":{"1":1800,"2":1800,"3":1800},
							"force":1800,
							"level":18
						},
					"19":{
							"attrs":{"1":1900,"2":1900,"3":1900},
							"force":1900,
							"level":19
						},
					"20":{
							"attrs":{"1":2000,"2":2000,"3":2000},
							"force":2000,
							"level":20
						},
					"21":{
							"attrs":{"1":2100,"2":2100,"3":2100},
							"force":2100,
							"level":21
						},
					"22":{
							"attrs":{"1":2200,"2":2200,"3":2200},
							"force":2200,
							"level":22
						},
					"23":{
							"attrs":{"1":2300,"2":2300,"3":2300},
							"force":2300,
							"level":23
						},
					"24":{
							"attrs":{"1":2400,"2":2400,"3":2400},
							"force":2400,
							"level":24
						},
					"25":{
							"attrs":{"1":2500,"2":2500,"3":2500},
							"force":2500,
							"level":25
						},
					"26":{
							"attrs":{"1":2600,"2":2600,"3":2600},
							"force":2600,
							"level":26
						},
					"27":{
							"attrs":{"1":2700,"2":2700,"3":2700},
							"force":2700,
							"level":27
						},
					"28":{
							"attrs":{"1":2800,"2":2800,"3":2800},
							"force":2800,
							"level":28
						},
					"29":{
							"attrs":{"1":2900,"2":2900,"3":2900},
							"force":2900,
							"level":29
						},
					"30":{
							"attrs":{"1":3000,"2":3000,"3":3000},
							"force":3000,
							"level":30
						},
					"31":{
							"attrs":{"1":3100,"2":3100,"3":3100},
							"force":3100,
							"level":31
						},
					"32":{
							"attrs":{"1":3200,"2":3200,"3":3200},
							"force":3200,
							"level":32
						},
					"33":{
							"attrs":{"1":3300,"2":3300,"3":3300},
							"force":3300,
							"level":33
						},
					"34":{
							"attrs":{"1":3400,"2":3400,"3":3400},
							"force":3400,
							"level":34
						},
					"35":{
							"attrs":{"1":3500,"2":3500,"3":3500},
							"force":3500,
							"level":35
						},
					"36":{
							"attrs":{"1":3600,"2":3600,"3":3600},
							"force":3600,
							"level":36
						},
					"37":{
							"attrs":{"1":3700,"2":3700,"3":3700},
							"force":3700,
							"level":37
						},
					"38":{
							"attrs":{"1":3800,"2":3800,"3":3800},
							"force":3800,
							"level":38
						},
					"39":{
							"attrs":{"1":3900,"2":3900,"3":3900},
							"force":3900,
							"level":39
						},
					"40":{
							"attrs":{"1":4000,"2":4000,"3":4000},
							"force":4000,
							"level":40
						},
					"41":{
							"attrs":{"1":4100,"2":4100,"3":4100},
							"force":4100,
							"level":41
						},
					"42":{
							"attrs":{"1":4200,"2":4200,"3":4200},
							"force":4200,
							"level":42
						},
					"43":{
							"attrs":{"1":4300,"2":4300,"3":4300},
							"force":4300,
							"level":43
						},
					"44":{
							"attrs":{"1":4400,"2":4400,"3":4400},
							"force":4400,
							"level":44
						},
					"45":{
							"attrs":{"1":4500,"2":4500,"3":4500},
							"force":4500,
							"level":45
						},
					"46":{
							"attrs":{"1":4600,"2":4600,"3":4600},
							"force":4600,
							"level":46
						},
					"47":{
							"attrs":{"1":4700,"2":4700,"3":4700},
							"force":4700,
							"level":47
						},
					"48":{
							"attrs":{"1":4800,"2":4800,"3":4800},
							"force":4800,
							"level":48
						},
					"49":{
							"attrs":{"1":4900,"2":4900,"3":4900},
							"force":4900,
							"level":49
						},
					"50":{
							"attrs":{"1":5000,"2":5000,"3":5000},
							"force":5000,
							"level":50
						}
				},
			"5":{
					"1":{
							"attrs":{"1":50,"2":50,"3":50},
							"force":100,
							"level":1
						},
					"2":{
							"attrs":{"1":100,"2":100,"3":100},
							"force":200,
							"level":2
						},
					"3":{
							"attrs":{"1":150,"2":150,"3":150},
							"force":300,
							"level":3
						},
					"4":{
							"attrs":{"1":200,"2":200,"3":200},
							"force":400,
							"level":4
						},
					"5":{
							"attrs":{"1":250,"2":250,"3":250},
							"force":500,
							"level":5
						},
					"6":{
							"attrs":{"1":300,"2":300,"3":300},
							"force":600,
							"level":6
						},
					"7":{
							"attrs":{"1":350,"2":350,"3":350},
							"force":700,
							"level":7
						},
					"8":{
							"attrs":{"1":400,"2":400,"3":400},
							"force":800,
							"level":8
						},
					"9":{
							"attrs":{"1":450,"2":450,"3":450},
							"force":900,
							"level":9
						},
					"10":{
							"attrs":{"1":500,"2":500,"3":500},
							"force":1000,
							"level":10
						},
					"11":{
							"attrs":{"1":550,"2":550,"3":550},
							"force":1100,
							"level":11
						},
					"12":{
							"attrs":{"1":600,"2":600,"3":600},
							"force":1200,
							"level":12
						},
					"13":{
							"attrs":{"1":650,"2":650,"3":650},
							"force":1300,
							"level":13
						},
					"14":{
							"attrs":{"1":700,"2":700,"3":700},
							"force":1400,
							"level":14
						},
					"15":{
							"attrs":{"1":750,"2":750,"3":750},
							"force":1500,
							"level":15
						},
					"16":{
							"attrs":{"1":800,"2":800,"3":800},
							"force":1600,
							"level":16
						},
					"17":{
							"attrs":{"1":850,"2":850,"3":850},
							"force":1700,
							"level":17
						},
					"18":{
							"attrs":{"1":900,"2":900,"3":900},
							"force":1800,
							"level":18
						},
					"19":{
							"attrs":{"1":950,"2":950,"3":950},
							"force":1900,
							"level":19
						},
					"20":{
							"attrs":{"1":1000,"2":1000,"3":1000},
							"force":2000,
							"level":20
						},
					"21":{
							"attrs":{"1":1050,"2":1050,"3":1050},
							"force":2100,
							"level":21
						},
					"22":{
							"attrs":{"1":1100,"2":1100,"3":1100},
							"force":2200,
							"level":22
						},
					"23":{
							"attrs":{"1":1150,"2":1150,"3":1150},
							"force":2300,
							"level":23
						},
					"24":{
							"attrs":{"1":1200,"2":1200,"3":1200},
							"force":2400,
							"level":24
						},
					"25":{
							"attrs":{"1":1250,"2":1250,"3":1250},
							"force":2500,
							"level":25
						},
					"26":{
							"attrs":{"1":1300,"2":1300,"3":1300},
							"force":2600,
							"level":26
						},
					"27":{
							"attrs":{"1":1350,"2":1350,"3":1350},
							"force":2700,
							"level":27
						},
					"28":{
							"attrs":{"1":1400,"2":1400,"3":1400},
							"force":2800,
							"level":28
						},
					"29":{
							"attrs":{"1":1450,"2":1450,"3":1450},
							"force":2900,
							"level":29
						},
					"30":{
							"attrs":{"1":1500,"2":1500,"3":1500},
							"force":3000,
							"level":30
						},
					"31":{
							"attrs":{"1":1550,"2":1550,"3":1550},
							"force":3100,
							"level":31
						},
					"32":{
							"attrs":{"1":1600,"2":1600,"3":1600},
							"force":3200,
							"level":32
						},
					"33":{
							"attrs":{"1":1650,"2":1650,"3":1650},
							"force":3300,
							"level":33
						},
					"34":{
							"attrs":{"1":1700,"2":1700,"3":1700},
							"force":3400,
							"level":34
						},
					"35":{
							"attrs":{"1":1750,"2":1750,"3":1750},
							"force":3500,
							"level":35
						},
					"36":{
							"attrs":{"1":1800,"2":1800,"3":1800},
							"force":3600,
							"level":36
						},
					"37":{
							"attrs":{"1":1850,"2":1850,"3":1850},
							"force":3700,
							"level":37
						},
					"38":{
							"attrs":{"1":1900,"2":1900,"3":1900},
							"force":3800,
							"level":38
						},
					"39":{
							"attrs":{"1":1950,"2":1950,"3":1950},
							"force":3900,
							"level":39
						},
					"40":{
							"attrs":{"1":2000,"2":2000,"3":2000},
							"force":4000,
							"level":40
						},
					"41":{
							"attrs":{"1":2050,"2":2050,"3":2050},
							"force":4100,
							"level":41
						},
					"42":{
							"attrs":{"1":2100,"2":2100,"3":2100},
							"force":4200,
							"level":42
						},
					"43":{
							"attrs":{"1":2150,"2":2150,"3":2150},
							"force":4300,
							"level":43
						},
					"44":{
							"attrs":{"1":2200,"2":2200,"3":2200},
							"force":4400,
							"level":44
						},
					"45":{
							"attrs":{"1":2250,"2":2250,"3":2250},
							"force":4500,
							"level":45
						},
					"46":{
							"attrs":{"1":2300,"2":2300,"3":2300},
							"force":4600,
							"level":46
						},
					"47":{
							"attrs":{"1":2350,"2":2350,"3":2350},
							"force":4700,
							"level":47
						},
					"48":{
							"attrs":{"1":2400,"2":2400,"3":2400},
							"force":4800,
							"level":48
						},
					"49":{
							"attrs":{"1":2450,"2":2450,"3":2450},
							"force":4900,
							"level":49
						},
					"50":{
							"attrs":{"1":2500,"2":2500,"3":2500},
							"force":5000,
							"level":50
						}
				},
			"6":{
					"1":{
							"attrs":{"1":50,"2":50,"3":50},
							"force":100,
							"level":1
						},
					"2":{
							"attrs":{"1":100,"2":100,"3":100},
							"force":200,
							"level":2
						},
					"3":{
							"attrs":{"1":150,"2":150,"3":150},
							"force":300,
							"level":3
						},
					"4":{
							"attrs":{"1":200,"2":200,"3":200},
							"force":400,
							"level":4
						},
					"5":{
							"attrs":{"1":250,"2":250,"3":250},
							"force":500,
							"level":5
						},
					"6":{
							"attrs":{"1":300,"2":300,"3":300},
							"force":600,
							"level":6
						},
					"7":{
							"attrs":{"1":350,"2":350,"3":350},
							"force":700,
							"level":7
						},
					"8":{
							"attrs":{"1":400,"2":400,"3":400},
							"force":800,
							"level":8
						},
					"9":{
							"attrs":{"1":450,"2":450,"3":450},
							"force":900,
							"level":9
						},
					"10":{
							"attrs":{"1":500,"2":500,"3":500},
							"force":1000,
							"level":10
						},
					"11":{
							"attrs":{"1":550,"2":550,"3":550},
							"force":1100,
							"level":11
						},
					"12":{
							"attrs":{"1":600,"2":600,"3":600},
							"force":1200,
							"level":12
						},
					"13":{
							"attrs":{"1":650,"2":650,"3":650},
							"force":1300,
							"level":13
						},
					"14":{
							"attrs":{"1":700,"2":700,"3":700},
							"force":1400,
							"level":14
						},
					"15":{
							"attrs":{"1":750,"2":750,"3":750},
							"force":1500,
							"level":15
						},
					"16":{
							"attrs":{"1":800,"2":800,"3":800},
							"force":1600,
							"level":16
						},
					"17":{
							"attrs":{"1":850,"2":850,"3":850},
							"force":1700,
							"level":17
						},
					"18":{
							"attrs":{"1":900,"2":900,"3":900},
							"force":1800,
							"level":18
						},
					"19":{
							"attrs":{"1":950,"2":950,"3":950},
							"force":1900,
							"level":19
						},
					"20":{
							"attrs":{"1":1000,"2":1000,"3":1000},
							"force":2000,
							"level":20
						},
					"21":{
							"attrs":{"1":1050,"2":1050,"3":1050},
							"force":2100,
							"level":21
						},
					"22":{
							"attrs":{"1":1100,"2":1100,"3":1100},
							"force":2200,
							"level":22
						},
					"23":{
							"attrs":{"1":1150,"2":1150,"3":1150},
							"force":2300,
							"level":23
						},
					"24":{
							"attrs":{"1":1200,"2":1200,"3":1200},
							"force":2400,
							"level":24
						},
					"25":{
							"attrs":{"1":1250,"2":1250,"3":1250},
							"force":2500,
							"level":25
						},
					"26":{
							"attrs":{"1":1300,"2":1300,"3":1300},
							"force":2600,
							"level":26
						},
					"27":{
							"attrs":{"1":1350,"2":1350,"3":1350},
							"force":2700,
							"level":27
						},
					"28":{
							"attrs":{"1":1400,"2":1400,"3":1400},
							"force":2800,
							"level":28
						},
					"29":{
							"attrs":{"1":1450,"2":1450,"3":1450},
							"force":2900,
							"level":29
						},
					"30":{
							"attrs":{"1":1500,"2":1500,"3":1500},
							"force":3000,
							"level":30
						},
					"31":{
							"attrs":{"1":1550,"2":1550,"3":1550},
							"force":3100,
							"level":31
						},
					"32":{
							"attrs":{"1":1600,"2":1600,"3":1600},
							"force":3200,
							"level":32
						},
					"33":{
							"attrs":{"1":1650,"2":1650,"3":1650},
							"force":3300,
							"level":33
						},
					"34":{
							"attrs":{"1":1700,"2":1700,"3":1700},
							"force":3400,
							"level":34
						},
					"35":{
							"attrs":{"1":1750,"2":1750,"3":1750},
							"force":3500,
							"level":35
						},
					"36":{
							"attrs":{"1":1800,"2":1800,"3":1800},
							"force":3600,
							"level":36
						},
					"37":{
							"attrs":{"1":1850,"2":1850,"3":1850},
							"force":3700,
							"level":37
						},
					"38":{
							"attrs":{"1":1900,"2":1900,"3":1900},
							"force":3800,
							"level":38
						},
					"39":{
							"attrs":{"1":1950,"2":1950,"3":1950},
							"force":3900,
							"level":39
						},
					"40":{
							"attrs":{"1":2000,"2":2000,"3":2000},
							"force":4000,
							"level":40
						},
					"41":{
							"attrs":{"1":2050,"2":2050,"3":2050},
							"force":4100,
							"level":41
						},
					"42":{
							"attrs":{"1":2100,"2":2100,"3":2100},
							"force":4200,
							"level":42
						},
					"43":{
							"attrs":{"1":2150,"2":2150,"3":2150},
							"force":4300,
							"level":43
						},
					"44":{
							"attrs":{"1":2200,"2":2200,"3":2200},
							"force":4400,
							"level":44
						},
					"45":{
							"attrs":{"1":2250,"2":2250,"3":2250},
							"force":4500,
							"level":45
						},
					"46":{
							"attrs":{"1":2300,"2":2300,"3":2300},
							"force":4600,
							"level":46
						},
					"47":{
							"attrs":{"1":2350,"2":2350,"3":2350},
							"force":4700,
							"level":47
						},
					"48":{
							"attrs":{"1":2400,"2":2400,"3":2400},
							"force":4800,
							"level":48
						},
					"49":{
							"attrs":{"1":2450,"2":2450,"3":2450},
							"force":4900,
							"level":49
						},
					"50":{
							"attrs":{"1":2500,"2":2500,"3":2500},
							"force":5000,
							"level":50
						}
				},
			"7":{
					"1":{
							"attrs":{"1":50,"2":50,"3":50},
							"force":100,
							"level":1
						},
					"2":{
							"attrs":{"1":100,"2":100,"3":100},
							"force":200,
							"level":2
						},
					"3":{
							"attrs":{"1":150,"2":150,"3":150},
							"force":300,
							"level":3
						},
					"4":{
							"attrs":{"1":200,"2":200,"3":200},
							"force":400,
							"level":4
						},
					"5":{
							"attrs":{"1":250,"2":250,"3":250},
							"force":500,
							"level":5
						},
					"6":{
							"attrs":{"1":300,"2":300,"3":300},
							"force":600,
							"level":6
						},
					"7":{
							"attrs":{"1":350,"2":350,"3":350},
							"force":700,
							"level":7
						},
					"8":{
							"attrs":{"1":400,"2":400,"3":400},
							"force":800,
							"level":8
						},
					"9":{
							"attrs":{"1":450,"2":450,"3":450},
							"force":900,
							"level":9
						},
					"10":{
							"attrs":{"1":500,"2":500,"3":500},
							"force":1000,
							"level":10
						},
					"11":{
							"attrs":{"1":550,"2":550,"3":550},
							"force":1100,
							"level":11
						},
					"12":{
							"attrs":{"1":600,"2":600,"3":600},
							"force":1200,
							"level":12
						},
					"13":{
							"attrs":{"1":650,"2":650,"3":650},
							"force":1300,
							"level":13
						},
					"14":{
							"attrs":{"1":700,"2":700,"3":700},
							"force":1400,
							"level":14
						},
					"15":{
							"attrs":{"1":750,"2":750,"3":750},
							"force":1500,
							"level":15
						},
					"16":{
							"attrs":{"1":800,"2":800,"3":800},
							"force":1600,
							"level":16
						},
					"17":{
							"attrs":{"1":850,"2":850,"3":850},
							"force":1700,
							"level":17
						},
					"18":{
							"attrs":{"1":900,"2":900,"3":900},
							"force":1800,
							"level":18
						},
					"19":{
							"attrs":{"1":950,"2":950,"3":950},
							"force":1900,
							"level":19
						},
					"20":{
							"attrs":{"1":1000,"2":1000,"3":1000},
							"force":2000,
							"level":20
						},
					"21":{
							"attrs":{"1":1050,"2":1050,"3":1050},
							"force":2100,
							"level":21
						},
					"22":{
							"attrs":{"1":1100,"2":1100,"3":1100},
							"force":2200,
							"level":22
						},
					"23":{
							"attrs":{"1":1150,"2":1150,"3":1150},
							"force":2300,
							"level":23
						},
					"24":{
							"attrs":{"1":1200,"2":1200,"3":1200},
							"force":2400,
							"level":24
						},
					"25":{
							"attrs":{"1":1250,"2":1250,"3":1250},
							"force":2500,
							"level":25
						},
					"26":{
							"attrs":{"1":1300,"2":1300,"3":1300},
							"force":2600,
							"level":26
						},
					"27":{
							"attrs":{"1":1350,"2":1350,"3":1350},
							"force":2700,
							"level":27
						},
					"28":{
							"attrs":{"1":1400,"2":1400,"3":1400},
							"force":2800,
							"level":28
						},
					"29":{
							"attrs":{"1":1450,"2":1450,"3":1450},
							"force":2900,
							"level":29
						},
					"30":{
							"attrs":{"1":1500,"2":1500,"3":1500},
							"force":3000,
							"level":30
						},
					"31":{
							"attrs":{"1":1550,"2":1550,"3":1550},
							"force":3100,
							"level":31
						},
					"32":{
							"attrs":{"1":1600,"2":1600,"3":1600},
							"force":3200,
							"level":32
						},
					"33":{
							"attrs":{"1":1650,"2":1650,"3":1650},
							"force":3300,
							"level":33
						},
					"34":{
							"attrs":{"1":1700,"2":1700,"3":1700},
							"force":3400,
							"level":34
						},
					"35":{
							"attrs":{"1":1750,"2":1750,"3":1750},
							"force":3500,
							"level":35
						},
					"36":{
							"attrs":{"1":1800,"2":1800,"3":1800},
							"force":3600,
							"level":36
						},
					"37":{
							"attrs":{"1":1850,"2":1850,"3":1850},
							"force":3700,
							"level":37
						},
					"38":{
							"attrs":{"1":1900,"2":1900,"3":1900},
							"force":3800,
							"level":38
						},
					"39":{
							"attrs":{"1":1950,"2":1950,"3":1950},
							"force":3900,
							"level":39
						},
					"40":{
							"attrs":{"1":2000,"2":2000,"3":2000},
							"force":4000,
							"level":40
						},
					"41":{
							"attrs":{"1":2050,"2":2050,"3":2050},
							"force":4100,
							"level":41
						},
					"42":{
							"attrs":{"1":2100,"2":2100,"3":2100},
							"force":4200,
							"level":42
						},
					"43":{
							"attrs":{"1":2150,"2":2150,"3":2150},
							"force":4300,
							"level":43
						},
					"44":{
							"attrs":{"1":2200,"2":2200,"3":2200},
							"force":4400,
							"level":44
						},
					"45":{
							"attrs":{"1":2250,"2":2250,"3":2250},
							"force":4500,
							"level":45
						},
					"46":{
							"attrs":{"1":2300,"2":2300,"3":2300},
							"force":4600,
							"level":46
						},
					"47":{
							"attrs":{"1":2350,"2":2350,"3":2350},
							"force":4700,
							"level":47
						},
					"48":{
							"attrs":{"1":2400,"2":2400,"3":2400},
							"force":4800,
							"level":48
						},
					"49":{
							"attrs":{"1":2450,"2":2450,"3":2450},
							"force":4900,
							"level":49
						},
					"50":{
							"attrs":{"1":2500,"2":2500,"3":2500},
							"force":5000,
							"level":50
						}
				},
			"8":{
					"1":{
							"attrs":{"1":50,"2":50,"3":50},
							"force":100,
							"level":1
						},
					"2":{
							"attrs":{"1":100,"2":100,"3":100},
							"force":200,
							"level":2
						},
					"3":{
							"attrs":{"1":150,"2":150,"3":150},
							"force":300,
							"level":3
						},
					"4":{
							"attrs":{"1":200,"2":200,"3":200},
							"force":400,
							"level":4
						},
					"5":{
							"attrs":{"1":250,"2":250,"3":250},
							"force":500,
							"level":5
						},
					"6":{
							"attrs":{"1":300,"2":300,"3":300},
							"force":600,
							"level":6
						},
					"7":{
							"attrs":{"1":350,"2":350,"3":350},
							"force":700,
							"level":7
						},
					"8":{
							"attrs":{"1":400,"2":400,"3":400},
							"force":800,
							"level":8
						},
					"9":{
							"attrs":{"1":450,"2":450,"3":450},
							"force":900,
							"level":9
						},
					"10":{
							"attrs":{"1":500,"2":500,"3":500},
							"force":1000,
							"level":10
						},
					"11":{
							"attrs":{"1":550,"2":550,"3":550},
							"force":1100,
							"level":11
						},
					"12":{
							"attrs":{"1":600,"2":600,"3":600},
							"force":1200,
							"level":12
						},
					"13":{
							"attrs":{"1":650,"2":650,"3":650},
							"force":1300,
							"level":13
						},
					"14":{
							"attrs":{"1":700,"2":700,"3":700},
							"force":1400,
							"level":14
						},
					"15":{
							"attrs":{"1":750,"2":750,"3":750},
							"force":1500,
							"level":15
						},
					"16":{
							"attrs":{"1":800,"2":800,"3":800},
							"force":1600,
							"level":16
						},
					"17":{
							"attrs":{"1":850,"2":850,"3":850},
							"force":1700,
							"level":17
						},
					"18":{
							"attrs":{"1":900,"2":900,"3":900},
							"force":1800,
							"level":18
						},
					"19":{
							"attrs":{"1":950,"2":950,"3":950},
							"force":1900,
							"level":19
						},
					"20":{
							"attrs":{"1":1000,"2":1000,"3":1000},
							"force":2000,
							"level":20
						},
					"21":{
							"attrs":{"1":1050,"2":1050,"3":1050},
							"force":2100,
							"level":21
						},
					"22":{
							"attrs":{"1":1100,"2":1100,"3":1100},
							"force":2200,
							"level":22
						},
					"23":{
							"attrs":{"1":1150,"2":1150,"3":1150},
							"force":2300,
							"level":23
						},
					"24":{
							"attrs":{"1":1200,"2":1200,"3":1200},
							"force":2400,
							"level":24
						},
					"25":{
							"attrs":{"1":1250,"2":1250,"3":1250},
							"force":2500,
							"level":25
						},
					"26":{
							"attrs":{"1":1300,"2":1300,"3":1300},
							"force":2600,
							"level":26
						},
					"27":{
							"attrs":{"1":1350,"2":1350,"3":1350},
							"force":2700,
							"level":27
						},
					"28":{
							"attrs":{"1":1400,"2":1400,"3":1400},
							"force":2800,
							"level":28
						},
					"29":{
							"attrs":{"1":1450,"2":1450,"3":1450},
							"force":2900,
							"level":29
						},
					"30":{
							"attrs":{"1":1500,"2":1500,"3":1500},
							"force":3000,
							"level":30
						},
					"31":{
							"attrs":{"1":1550,"2":1550,"3":1550},
							"force":3100,
							"level":31
						},
					"32":{
							"attrs":{"1":1600,"2":1600,"3":1600},
							"force":3200,
							"level":32
						},
					"33":{
							"attrs":{"1":1650,"2":1650,"3":1650},
							"force":3300,
							"level":33
						},
					"34":{
							"attrs":{"1":1700,"2":1700,"3":1700},
							"force":3400,
							"level":34
						},
					"35":{
							"attrs":{"1":1750,"2":1750,"3":1750},
							"force":3500,
							"level":35
						},
					"36":{
							"attrs":{"1":1800,"2":1800,"3":1800},
							"force":3600,
							"level":36
						},
					"37":{
							"attrs":{"1":1850,"2":1850,"3":1850},
							"force":3700,
							"level":37
						},
					"38":{
							"attrs":{"1":1900,"2":1900,"3":1900},
							"force":3800,
							"level":38
						},
					"39":{
							"attrs":{"1":1950,"2":1950,"3":1950},
							"force":3900,
							"level":39
						},
					"40":{
							"attrs":{"1":2000,"2":2000,"3":2000},
							"force":4000,
							"level":40
						},
					"41":{
							"attrs":{"1":2050,"2":2050,"3":2050},
							"force":4100,
							"level":41
						},
					"42":{
							"attrs":{"1":2100,"2":2100,"3":2100},
							"force":4200,
							"level":42
						},
					"43":{
							"attrs":{"1":2150,"2":2150,"3":2150},
							"force":4300,
							"level":43
						},
					"44":{
							"attrs":{"1":2200,"2":2200,"3":2200},
							"force":4400,
							"level":44
						},
					"45":{
							"attrs":{"1":2250,"2":2250,"3":2250},
							"force":4500,
							"level":45
						},
					"46":{
							"attrs":{"1":2300,"2":2300,"3":2300},
							"force":4600,
							"level":46
						},
					"47":{
							"attrs":{"1":2350,"2":2350,"3":2350},
							"force":4700,
							"level":47
						},
					"48":{
							"attrs":{"1":2400,"2":2400,"3":2400},
							"force":4800,
							"level":48
						},
					"49":{
							"attrs":{"1":2450,"2":2450,"3":2450},
							"force":4900,
							"level":49
						},
					"50":{
							"attrs":{"1":2500,"2":2500,"3":2500},
							"force":5000,
							"level":50
						}
				},
			"9":{
					"1":{
							"attrs":{"1":50,"2":50,"3":50},
							"force":100,
							"level":1
						},
					"2":{
							"attrs":{"1":100,"2":100,"3":100},
							"force":200,
							"level":2
						},
					"3":{
							"attrs":{"1":150,"2":150,"3":150},
							"force":300,
							"level":3
						},
					"4":{
							"attrs":{"1":200,"2":200,"3":200},
							"force":400,
							"level":4
						},
					"5":{
							"attrs":{"1":250,"2":250,"3":250},
							"force":500,
							"level":5
						},
					"6":{
							"attrs":{"1":300,"2":300,"3":300},
							"force":600,
							"level":6
						},
					"7":{
							"attrs":{"1":350,"2":350,"3":350},
							"force":700,
							"level":7
						},
					"8":{
							"attrs":{"1":400,"2":400,"3":400},
							"force":800,
							"level":8
						},
					"9":{
							"attrs":{"1":450,"2":450,"3":450},
							"force":900,
							"level":9
						},
					"10":{
							"attrs":{"1":500,"2":500,"3":500},
							"force":1000,
							"level":10
						},
					"11":{
							"attrs":{"1":550,"2":550,"3":550},
							"force":1100,
							"level":11
						},
					"12":{
							"attrs":{"1":600,"2":600,"3":600},
							"force":1200,
							"level":12
						},
					"13":{
							"attrs":{"1":650,"2":650,"3":650},
							"force":1300,
							"level":13
						},
					"14":{
							"attrs":{"1":700,"2":700,"3":700},
							"force":1400,
							"level":14
						},
					"15":{
							"attrs":{"1":750,"2":750,"3":750},
							"force":1500,
							"level":15
						},
					"16":{
							"attrs":{"1":800,"2":800,"3":800},
							"force":1600,
							"level":16
						},
					"17":{
							"attrs":{"1":850,"2":850,"3":850},
							"force":1700,
							"level":17
						},
					"18":{
							"attrs":{"1":900,"2":900,"3":900},
							"force":1800,
							"level":18
						},
					"19":{
							"attrs":{"1":950,"2":950,"3":950},
							"force":1900,
							"level":19
						},
					"20":{
							"attrs":{"1":1000,"2":1000,"3":1000},
							"force":2000,
							"level":20
						},
					"21":{
							"attrs":{"1":1050,"2":1050,"3":1050},
							"force":2100,
							"level":21
						},
					"22":{
							"attrs":{"1":1100,"2":1100,"3":1100},
							"force":2200,
							"level":22
						},
					"23":{
							"attrs":{"1":1150,"2":1150,"3":1150},
							"force":2300,
							"level":23
						},
					"24":{
							"attrs":{"1":1200,"2":1200,"3":1200},
							"force":2400,
							"level":24
						},
					"25":{
							"attrs":{"1":1250,"2":1250,"3":1250},
							"force":2500,
							"level":25
						},
					"26":{
							"attrs":{"1":1300,"2":1300,"3":1300},
							"force":2600,
							"level":26
						},
					"27":{
							"attrs":{"1":1350,"2":1350,"3":1350},
							"force":2700,
							"level":27
						},
					"28":{
							"attrs":{"1":1400,"2":1400,"3":1400},
							"force":2800,
							"level":28
						},
					"29":{
							"attrs":{"1":1450,"2":1450,"3":1450},
							"force":2900,
							"level":29
						},
					"30":{
							"attrs":{"1":1500,"2":1500,"3":1500},
							"force":3000,
							"level":30
						},
					"31":{
							"attrs":{"1":1550,"2":1550,"3":1550},
							"force":3100,
							"level":31
						},
					"32":{
							"attrs":{"1":1600,"2":1600,"3":1600},
							"force":3200,
							"level":32
						},
					"33":{
							"attrs":{"1":1650,"2":1650,"3":1650},
							"force":3300,
							"level":33
						},
					"34":{
							"attrs":{"1":1700,"2":1700,"3":1700},
							"force":3400,
							"level":34
						},
					"35":{
							"attrs":{"1":1750,"2":1750,"3":1750},
							"force":3500,
							"level":35
						},
					"36":{
							"attrs":{"1":1800,"2":1800,"3":1800},
							"force":3600,
							"level":36
						},
					"37":{
							"attrs":{"1":1850,"2":1850,"3":1850},
							"force":3700,
							"level":37
						},
					"38":{
							"attrs":{"1":1900,"2":1900,"3":1900},
							"force":3800,
							"level":38
						},
					"39":{
							"attrs":{"1":1950,"2":1950,"3":1950},
							"force":3900,
							"level":39
						},
					"40":{
							"attrs":{"1":2000,"2":2000,"3":2000},
							"force":4000,
							"level":40
						},
					"41":{
							"attrs":{"1":2050,"2":2050,"3":2050},
							"force":4100,
							"level":41
						},
					"42":{
							"attrs":{"1":2100,"2":2100,"3":2100},
							"force":4200,
							"level":42
						},
					"43":{
							"attrs":{"1":2150,"2":2150,"3":2150},
							"force":4300,
							"level":43
						},
					"44":{
							"attrs":{"1":2200,"2":2200,"3":2200},
							"force":4400,
							"level":44
						},
					"45":{
							"attrs":{"1":2250,"2":2250,"3":2250},
							"force":4500,
							"level":45
						},
					"46":{
							"attrs":{"1":2300,"2":2300,"3":2300},
							"force":4600,
							"level":46
						},
					"47":{
							"attrs":{"1":2350,"2":2350,"3":2350},
							"force":4700,
							"level":47
						},
					"48":{
							"attrs":{"1":2400,"2":2400,"3":2400},
							"force":4800,
							"level":48
						},
					"49":{
							"attrs":{"1":2450,"2":2450,"3":2450},
							"force":4900,
							"level":49
						},
					"50":{
							"attrs":{"1":2500,"2":2500,"3":2500},
							"force":5000,
							"level":50
						}
				},
			"10":{
					"1":{
							"attrs":{"1":50,"2":50,"3":50},
							"force":100,
							"level":1
						},
					"2":{
							"attrs":{"1":100,"2":100,"3":100},
							"force":200,
							"level":2
						},
					"3":{
							"attrs":{"1":150,"2":150,"3":150},
							"force":300,
							"level":3
						},
					"4":{
							"attrs":{"1":200,"2":200,"3":200},
							"force":400,
							"level":4
						},
					"5":{
							"attrs":{"1":250,"2":250,"3":250},
							"force":500,
							"level":5
						},
					"6":{
							"attrs":{"1":300,"2":300,"3":300},
							"force":600,
							"level":6
						},
					"7":{
							"attrs":{"1":350,"2":350,"3":350},
							"force":700,
							"level":7
						},
					"8":{
							"attrs":{"1":400,"2":400,"3":400},
							"force":800,
							"level":8
						},
					"9":{
							"attrs":{"1":450,"2":450,"3":450},
							"force":900,
							"level":9
						},
					"10":{
							"attrs":{"1":500,"2":500,"3":500},
							"force":1000,
							"level":10
						},
					"11":{
							"attrs":{"1":550,"2":550,"3":550},
							"force":1100,
							"level":11
						},
					"12":{
							"attrs":{"1":600,"2":600,"3":600},
							"force":1200,
							"level":12
						},
					"13":{
							"attrs":{"1":650,"2":650,"3":650},
							"force":1300,
							"level":13
						},
					"14":{
							"attrs":{"1":700,"2":700,"3":700},
							"force":1400,
							"level":14
						},
					"15":{
							"attrs":{"1":750,"2":750,"3":750},
							"force":1500,
							"level":15
						},
					"16":{
							"attrs":{"1":800,"2":800,"3":800},
							"force":1600,
							"level":16
						},
					"17":{
							"attrs":{"1":850,"2":850,"3":850},
							"force":1700,
							"level":17
						},
					"18":{
							"attrs":{"1":900,"2":900,"3":900},
							"force":1800,
							"level":18
						},
					"19":{
							"attrs":{"1":950,"2":950,"3":950},
							"force":1900,
							"level":19
						},
					"20":{
							"attrs":{"1":1000,"2":1000,"3":1000},
							"force":2000,
							"level":20
						},
					"21":{
							"attrs":{"1":1050,"2":1050,"3":1050},
							"force":2100,
							"level":21
						},
					"22":{
							"attrs":{"1":1100,"2":1100,"3":1100},
							"force":2200,
							"level":22
						},
					"23":{
							"attrs":{"1":1150,"2":1150,"3":1150},
							"force":2300,
							"level":23
						},
					"24":{
							"attrs":{"1":1200,"2":1200,"3":1200},
							"force":2400,
							"level":24
						},
					"25":{
							"attrs":{"1":1250,"2":1250,"3":1250},
							"force":2500,
							"level":25
						},
					"26":{
							"attrs":{"1":1300,"2":1300,"3":1300},
							"force":2600,
							"level":26
						},
					"27":{
							"attrs":{"1":1350,"2":1350,"3":1350},
							"force":2700,
							"level":27
						},
					"28":{
							"attrs":{"1":1400,"2":1400,"3":1400},
							"force":2800,
							"level":28
						},
					"29":{
							"attrs":{"1":1450,"2":1450,"3":1450},
							"force":2900,
							"level":29
						},
					"30":{
							"attrs":{"1":1500,"2":1500,"3":1500},
							"force":3000,
							"level":30
						},
					"31":{
							"attrs":{"1":1550,"2":1550,"3":1550},
							"force":3100,
							"level":31
						},
					"32":{
							"attrs":{"1":1600,"2":1600,"3":1600},
							"force":3200,
							"level":32
						},
					"33":{
							"attrs":{"1":1650,"2":1650,"3":1650},
							"force":3300,
							"level":33
						},
					"34":{
							"attrs":{"1":1700,"2":1700,"3":1700},
							"force":3400,
							"level":34
						},
					"35":{
							"attrs":{"1":1750,"2":1750,"3":1750},
							"force":3500,
							"level":35
						},
					"36":{
							"attrs":{"1":1800,"2":1800,"3":1800},
							"force":3600,
							"level":36
						},
					"37":{
							"attrs":{"1":1850,"2":1850,"3":1850},
							"force":3700,
							"level":37
						},
					"38":{
							"attrs":{"1":1900,"2":1900,"3":1900},
							"force":3800,
							"level":38
						},
					"39":{
							"attrs":{"1":1950,"2":1950,"3":1950},
							"force":3900,
							"level":39
						},
					"40":{
							"attrs":{"1":2000,"2":2000,"3":2000},
							"force":4000,
							"level":40
						},
					"41":{
							"attrs":{"1":2050,"2":2050,"3":2050},
							"force":4100,
							"level":41
						},
					"42":{
							"attrs":{"1":2100,"2":2100,"3":2100},
							"force":4200,
							"level":42
						},
					"43":{
							"attrs":{"1":2150,"2":2150,"3":2150},
							"force":4300,
							"level":43
						},
					"44":{
							"attrs":{"1":2200,"2":2200,"3":2200},
							"force":4400,
							"level":44
						},
					"45":{
							"attrs":{"1":2250,"2":2250,"3":2250},
							"force":4500,
							"level":45
						},
					"46":{
							"attrs":{"1":2300,"2":2300,"3":2300},
							"force":4600,
							"level":46
						},
					"47":{
							"attrs":{"1":2350,"2":2350,"3":2350},
							"force":4700,
							"level":47
						},
					"48":{
							"attrs":{"1":2400,"2":2400,"3":2400},
							"force":4800,
							"level":48
						},
					"49":{
							"attrs":{"1":2450,"2":2450,"3":2450},
							"force":4900,
							"level":49
						},
					"50":{
							"attrs":{"1":2500,"2":2500,"3":2500},
							"force":5000,
							"level":50
						}
				},
			"11":{
					"1":{
							"attrs":{"1":50,"2":50,"3":50},
							"force":100,
							"level":1
						},
					"2":{
							"attrs":{"1":100,"2":100,"3":100},
							"force":200,
							"level":2
						},
					"3":{
							"attrs":{"1":150,"2":150,"3":150},
							"force":300,
							"level":3
						},
					"4":{
							"attrs":{"1":200,"2":200,"3":200},
							"force":400,
							"level":4
						},
					"5":{
							"attrs":{"1":250,"2":250,"3":250},
							"force":500,
							"level":5
						},
					"6":{
							"attrs":{"1":300,"2":300,"3":300},
							"force":600,
							"level":6
						},
					"7":{
							"attrs":{"1":350,"2":350,"3":350},
							"force":700,
							"level":7
						},
					"8":{
							"attrs":{"1":400,"2":400,"3":400},
							"force":800,
							"level":8
						},
					"9":{
							"attrs":{"1":450,"2":450,"3":450},
							"force":900,
							"level":9
						},
					"10":{
							"attrs":{"1":500,"2":500,"3":500},
							"force":1000,
							"level":10
						},
					"11":{
							"attrs":{"1":550,"2":550,"3":550},
							"force":1100,
							"level":11
						},
					"12":{
							"attrs":{"1":600,"2":600,"3":600},
							"force":1200,
							"level":12
						},
					"13":{
							"attrs":{"1":650,"2":650,"3":650},
							"force":1300,
							"level":13
						},
					"14":{
							"attrs":{"1":700,"2":700,"3":700},
							"force":1400,
							"level":14
						},
					"15":{
							"attrs":{"1":750,"2":750,"3":750},
							"force":1500,
							"level":15
						},
					"16":{
							"attrs":{"1":800,"2":800,"3":800},
							"force":1600,
							"level":16
						},
					"17":{
							"attrs":{"1":850,"2":850,"3":850},
							"force":1700,
							"level":17
						},
					"18":{
							"attrs":{"1":900,"2":900,"3":900},
							"force":1800,
							"level":18
						},
					"19":{
							"attrs":{"1":950,"2":950,"3":950},
							"force":1900,
							"level":19
						},
					"20":{
							"attrs":{"1":1000,"2":1000,"3":1000},
							"force":2000,
							"level":20
						},
					"21":{
							"attrs":{"1":1050,"2":1050,"3":1050},
							"force":2100,
							"level":21
						},
					"22":{
							"attrs":{"1":1100,"2":1100,"3":1100},
							"force":2200,
							"level":22
						},
					"23":{
							"attrs":{"1":1150,"2":1150,"3":1150},
							"force":2300,
							"level":23
						},
					"24":{
							"attrs":{"1":1200,"2":1200,"3":1200},
							"force":2400,
							"level":24
						},
					"25":{
							"attrs":{"1":1250,"2":1250,"3":1250},
							"force":2500,
							"level":25
						},
					"26":{
							"attrs":{"1":1300,"2":1300,"3":1300},
							"force":2600,
							"level":26
						},
					"27":{
							"attrs":{"1":1350,"2":1350,"3":1350},
							"force":2700,
							"level":27
						},
					"28":{
							"attrs":{"1":1400,"2":1400,"3":1400},
							"force":2800,
							"level":28
						},
					"29":{
							"attrs":{"1":1450,"2":1450,"3":1450},
							"force":2900,
							"level":29
						},
					"30":{
							"attrs":{"1":1500,"2":1500,"3":1500},
							"force":3000,
							"level":30
						},
					"31":{
							"attrs":{"1":1550,"2":1550,"3":1550},
							"force":3100,
							"level":31
						},
					"32":{
							"attrs":{"1":1600,"2":1600,"3":1600},
							"force":3200,
							"level":32
						},
					"33":{
							"attrs":{"1":1650,"2":1650,"3":1650},
							"force":3300,
							"level":33
						},
					"34":{
							"attrs":{"1":1700,"2":1700,"3":1700},
							"force":3400,
							"level":34
						},
					"35":{
							"attrs":{"1":1750,"2":1750,"3":1750},
							"force":3500,
							"level":35
						},
					"36":{
							"attrs":{"1":1800,"2":1800,"3":1800},
							"force":3600,
							"level":36
						},
					"37":{
							"attrs":{"1":1850,"2":1850,"3":1850},
							"force":3700,
							"level":37
						},
					"38":{
							"attrs":{"1":1900,"2":1900,"3":1900},
							"force":3800,
							"level":38
						},
					"39":{
							"attrs":{"1":1950,"2":1950,"3":1950},
							"force":3900,
							"level":39
						},
					"40":{
							"attrs":{"1":2000,"2":2000,"3":2000},
							"force":4000,
							"level":40
						},
					"41":{
							"attrs":{"1":2050,"2":2050,"3":2050},
							"force":4100,
							"level":41
						},
					"42":{
							"attrs":{"1":2100,"2":2100,"3":2100},
							"force":4200,
							"level":42
						},
					"43":{
							"attrs":{"1":2150,"2":2150,"3":2150},
							"force":4300,
							"level":43
						},
					"44":{
							"attrs":{"1":2200,"2":2200,"3":2200},
							"force":4400,
							"level":44
						},
					"45":{
							"attrs":{"1":2250,"2":2250,"3":2250},
							"force":4500,
							"level":45
						},
					"46":{
							"attrs":{"1":2300,"2":2300,"3":2300},
							"force":4600,
							"level":46
						},
					"47":{
							"attrs":{"1":2350,"2":2350,"3":2350},
							"force":4700,
							"level":47
						},
					"48":{
							"attrs":{"1":2400,"2":2400,"3":2400},
							"force":4800,
							"level":48
						},
					"49":{
							"attrs":{"1":2450,"2":2450,"3":2450},
							"force":4900,
							"level":49
						},
					"50":{
							"attrs":{"1":2500,"2":2500,"3":2500},
							"force":5000,
							"level":50
						}
				},
			"12":{
					"1":{
							"attrs":{"1":50,"2":50,"3":50},
							"force":100,
							"level":1
						},
					"2":{
							"attrs":{"1":100,"2":100,"3":100},
							"force":200,
							"level":2
						},
					"3":{
							"attrs":{"1":150,"2":150,"3":150},
							"force":300,
							"level":3
						},
					"4":{
							"attrs":{"1":200,"2":200,"3":200},
							"force":400,
							"level":4
						},
					"5":{
							"attrs":{"1":250,"2":250,"3":250},
							"force":500,
							"level":5
						},
					"6":{
							"attrs":{"1":300,"2":300,"3":300},
							"force":600,
							"level":6
						},
					"7":{
							"attrs":{"1":350,"2":350,"3":350},
							"force":700,
							"level":7
						},
					"8":{
							"attrs":{"1":400,"2":400,"3":400},
							"force":800,
							"level":8
						},
					"9":{
							"attrs":{"1":450,"2":450,"3":450},
							"force":900,
							"level":9
						},
					"10":{
							"attrs":{"1":500,"2":500,"3":500},
							"force":1000,
							"level":10
						},
					"11":{
							"attrs":{"1":550,"2":550,"3":550},
							"force":1100,
							"level":11
						},
					"12":{
							"attrs":{"1":600,"2":600,"3":600},
							"force":1200,
							"level":12
						},
					"13":{
							"attrs":{"1":650,"2":650,"3":650},
							"force":1300,
							"level":13
						},
					"14":{
							"attrs":{"1":700,"2":700,"3":700},
							"force":1400,
							"level":14
						},
					"15":{
							"attrs":{"1":750,"2":750,"3":750},
							"force":1500,
							"level":15
						},
					"16":{
							"attrs":{"1":800,"2":800,"3":800},
							"force":1600,
							"level":16
						},
					"17":{
							"attrs":{"1":850,"2":850,"3":850},
							"force":1700,
							"level":17
						},
					"18":{
							"attrs":{"1":900,"2":900,"3":900},
							"force":1800,
							"level":18
						},
					"19":{
							"attrs":{"1":950,"2":950,"3":950},
							"force":1900,
							"level":19
						},
					"20":{
							"attrs":{"1":1000,"2":1000,"3":1000},
							"force":2000,
							"level":20
						},
					"21":{
							"attrs":{"1":1050,"2":1050,"3":1050},
							"force":2100,
							"level":21
						},
					"22":{
							"attrs":{"1":1100,"2":1100,"3":1100},
							"force":2200,
							"level":22
						},
					"23":{
							"attrs":{"1":1150,"2":1150,"3":1150},
							"force":2300,
							"level":23
						},
					"24":{
							"attrs":{"1":1200,"2":1200,"3":1200},
							"force":2400,
							"level":24
						},
					"25":{
							"attrs":{"1":1250,"2":1250,"3":1250},
							"force":2500,
							"level":25
						},
					"26":{
							"attrs":{"1":1300,"2":1300,"3":1300},
							"force":2600,
							"level":26
						},
					"27":{
							"attrs":{"1":1350,"2":1350,"3":1350},
							"force":2700,
							"level":27
						},
					"28":{
							"attrs":{"1":1400,"2":1400,"3":1400},
							"force":2800,
							"level":28
						},
					"29":{
							"attrs":{"1":1450,"2":1450,"3":1450},
							"force":2900,
							"level":29
						},
					"30":{
							"attrs":{"1":1500,"2":1500,"3":1500},
							"force":3000,
							"level":30
						},
					"31":{
							"attrs":{"1":1550,"2":1550,"3":1550},
							"force":3100,
							"level":31
						},
					"32":{
							"attrs":{"1":1600,"2":1600,"3":1600},
							"force":3200,
							"level":32
						},
					"33":{
							"attrs":{"1":1650,"2":1650,"3":1650},
							"force":3300,
							"level":33
						},
					"34":{
							"attrs":{"1":1700,"2":1700,"3":1700},
							"force":3400,
							"level":34
						},
					"35":{
							"attrs":{"1":1750,"2":1750,"3":1750},
							"force":3500,
							"level":35
						},
					"36":{
							"attrs":{"1":1800,"2":1800,"3":1800},
							"force":3600,
							"level":36
						},
					"37":{
							"attrs":{"1":1850,"2":1850,"3":1850},
							"force":3700,
							"level":37
						},
					"38":{
							"attrs":{"1":1900,"2":1900,"3":1900},
							"force":3800,
							"level":38
						},
					"39":{
							"attrs":{"1":1950,"2":1950,"3":1950},
							"force":3900,
							"level":39
						},
					"40":{
							"attrs":{"1":2000,"2":2000,"3":2000},
							"force":4000,
							"level":40
						},
					"41":{
							"attrs":{"1":2050,"2":2050,"3":2050},
							"force":4100,
							"level":41
						},
					"42":{
							"attrs":{"1":2100,"2":2100,"3":2100},
							"force":4200,
							"level":42
						},
					"43":{
							"attrs":{"1":2150,"2":2150,"3":2150},
							"force":4300,
							"level":43
						},
					"44":{
							"attrs":{"1":2200,"2":2200,"3":2200},
							"force":4400,
							"level":44
						},
					"45":{
							"attrs":{"1":2250,"2":2250,"3":2250},
							"force":4500,
							"level":45
						},
					"46":{
							"attrs":{"1":2300,"2":2300,"3":2300},
							"force":4600,
							"level":46
						},
					"47":{
							"attrs":{"1":2350,"2":2350,"3":2350},
							"force":4700,
							"level":47
						},
					"48":{
							"attrs":{"1":2400,"2":2400,"3":2400},
							"force":4800,
							"level":48
						},
					"49":{
							"attrs":{"1":2450,"2":2450,"3":2450},
							"force":4900,
							"level":49
						},
					"50":{
							"attrs":{"1":2500,"2":2500,"3":2500},
							"force":5000,
							"level":50
						}
				},
			"13":{
					"1":{
							"attrs":{"1":30,"2":30,"3":30},
							"force":100,
							"level":1
						},
					"2":{
							"attrs":{"1":60,"2":60,"3":60},
							"force":200,
							"level":2
						},
					"3":{
							"attrs":{"1":90,"2":90,"3":90},
							"force":300,
							"level":3
						},
					"4":{
							"attrs":{"1":120,"2":120,"3":120},
							"force":400,
							"level":4
						},
					"5":{
							"attrs":{"1":150,"2":150,"3":150},
							"force":500,
							"level":5
						},
					"6":{
							"attrs":{"1":180,"2":180,"3":180},
							"force":600,
							"level":6
						},
					"7":{
							"attrs":{"1":210,"2":210,"3":210},
							"force":700,
							"level":7
						},
					"8":{
							"attrs":{"1":240,"2":240,"3":240},
							"force":800,
							"level":8
						},
					"9":{
							"attrs":{"1":270,"2":270,"3":270},
							"force":900,
							"level":9
						},
					"10":{
							"attrs":{"1":300,"2":300,"3":300},
							"force":1000,
							"level":10
						},
					"11":{
							"attrs":{"1":330,"2":330,"3":330},
							"force":1100,
							"level":11
						},
					"12":{
							"attrs":{"1":360,"2":360,"3":360},
							"force":1200,
							"level":12
						},
					"13":{
							"attrs":{"1":390,"2":390,"3":390},
							"force":1300,
							"level":13
						},
					"14":{
							"attrs":{"1":420,"2":420,"3":420},
							"force":1400,
							"level":14
						},
					"15":{
							"attrs":{"1":450,"2":450,"3":450},
							"force":1500,
							"level":15
						},
					"16":{
							"attrs":{"1":480,"2":480,"3":480},
							"force":1600,
							"level":16
						},
					"17":{
							"attrs":{"1":510,"2":510,"3":510},
							"force":1700,
							"level":17
						},
					"18":{
							"attrs":{"1":540,"2":540,"3":540},
							"force":1800,
							"level":18
						},
					"19":{
							"attrs":{"1":570,"2":570,"3":570},
							"force":1900,
							"level":19
						},
					"20":{
							"attrs":{"1":600,"2":600,"3":600},
							"force":2000,
							"level":20
						},
					"21":{
							"attrs":{"1":630,"2":630,"3":630},
							"force":2100,
							"level":21
						},
					"22":{
							"attrs":{"1":660,"2":660,"3":660},
							"force":2200,
							"level":22
						},
					"23":{
							"attrs":{"1":690,"2":690,"3":690},
							"force":2300,
							"level":23
						},
					"24":{
							"attrs":{"1":720,"2":720,"3":720},
							"force":2400,
							"level":24
						},
					"25":{
							"attrs":{"1":750,"2":750,"3":750},
							"force":2500,
							"level":25
						},
					"26":{
							"attrs":{"1":780,"2":780,"3":780},
							"force":2600,
							"level":26
						},
					"27":{
							"attrs":{"1":810,"2":810,"3":810},
							"force":2700,
							"level":27
						},
					"28":{
							"attrs":{"1":840,"2":840,"3":840},
							"force":2800,
							"level":28
						},
					"29":{
							"attrs":{"1":870,"2":870,"3":870},
							"force":2900,
							"level":29
						},
					"30":{
							"attrs":{"1":900,"2":900,"3":900},
							"force":3000,
							"level":30
						},
					"31":{
							"attrs":{"1":930,"2":930,"3":930},
							"force":3100,
							"level":31
						},
					"32":{
							"attrs":{"1":960,"2":960,"3":960},
							"force":3200,
							"level":32
						},
					"33":{
							"attrs":{"1":990,"2":990,"3":990},
							"force":3300,
							"level":33
						},
					"34":{
							"attrs":{"1":1020,"2":1020,"3":1020},
							"force":3400,
							"level":34
						},
					"35":{
							"attrs":{"1":1050,"2":1050,"3":1050},
							"force":3500,
							"level":35
						},
					"36":{
							"attrs":{"1":1080,"2":1080,"3":1080},
							"force":3600,
							"level":36
						},
					"37":{
							"attrs":{"1":1110,"2":1110,"3":1110},
							"force":3700,
							"level":37
						},
					"38":{
							"attrs":{"1":1140,"2":1140,"3":1140},
							"force":3800,
							"level":38
						},
					"39":{
							"attrs":{"1":1170,"2":1170,"3":1170},
							"force":3900,
							"level":39
						},
					"40":{
							"attrs":{"1":1200,"2":1200,"3":1200},
							"force":4000,
							"level":40
						},
					"41":{
							"attrs":{"1":1230,"2":1230,"3":1230},
							"force":4100,
							"level":41
						},
					"42":{
							"attrs":{"1":1260,"2":1260,"3":1260},
							"force":4200,
							"level":42
						},
					"43":{
							"attrs":{"1":1290,"2":1290,"3":1290},
							"force":4300,
							"level":43
						},
					"44":{
							"attrs":{"1":1320,"2":1320,"3":1320},
							"force":4400,
							"level":44
						},
					"45":{
							"attrs":{"1":1350,"2":1350,"3":1350},
							"force":4500,
							"level":45
						},
					"46":{
							"attrs":{"1":1380,"2":1380,"3":1380},
							"force":4600,
							"level":46
						},
					"47":{
							"attrs":{"1":1410,"2":1410,"3":1410},
							"force":4700,
							"level":47
						},
					"48":{
							"attrs":{"1":1440,"2":1440,"3":1440},
							"force":4800,
							"level":48
						},
					"49":{
							"attrs":{"1":1470,"2":1470,"3":1470},
							"force":4900,
							"level":49
						},
					"50":{
							"attrs":{"1":1500,"2":1500,"3":1500},
							"force":5000,
							"level":50
						}
				},
			"14":{
					"1":{
							"attrs":{"1":30,"2":30,"3":30},
							"force":100,
							"level":1
						},
					"2":{
							"attrs":{"1":60,"2":60,"3":60},
							"force":200,
							"level":2
						},
					"3":{
							"attrs":{"1":90,"2":90,"3":90},
							"force":300,
							"level":3
						},
					"4":{
							"attrs":{"1":120,"2":120,"3":120},
							"force":400,
							"level":4
						},
					"5":{
							"attrs":{"1":150,"2":150,"3":150},
							"force":500,
							"level":5
						},
					"6":{
							"attrs":{"1":180,"2":180,"3":180},
							"force":600,
							"level":6
						},
					"7":{
							"attrs":{"1":210,"2":210,"3":210},
							"force":700,
							"level":7
						},
					"8":{
							"attrs":{"1":240,"2":240,"3":240},
							"force":800,
							"level":8
						},
					"9":{
							"attrs":{"1":270,"2":270,"3":270},
							"force":900,
							"level":9
						},
					"10":{
							"attrs":{"1":300,"2":300,"3":300},
							"force":1000,
							"level":10
						},
					"11":{
							"attrs":{"1":330,"2":330,"3":330},
							"force":1100,
							"level":11
						},
					"12":{
							"attrs":{"1":360,"2":360,"3":360},
							"force":1200,
							"level":12
						},
					"13":{
							"attrs":{"1":390,"2":390,"3":390},
							"force":1300,
							"level":13
						},
					"14":{
							"attrs":{"1":420,"2":420,"3":420},
							"force":1400,
							"level":14
						},
					"15":{
							"attrs":{"1":450,"2":450,"3":450},
							"force":1500,
							"level":15
						},
					"16":{
							"attrs":{"1":480,"2":480,"3":480},
							"force":1600,
							"level":16
						},
					"17":{
							"attrs":{"1":510,"2":510,"3":510},
							"force":1700,
							"level":17
						},
					"18":{
							"attrs":{"1":540,"2":540,"3":540},
							"force":1800,
							"level":18
						},
					"19":{
							"attrs":{"1":570,"2":570,"3":570},
							"force":1900,
							"level":19
						},
					"20":{
							"attrs":{"1":600,"2":600,"3":600},
							"force":2000,
							"level":20
						},
					"21":{
							"attrs":{"1":630,"2":630,"3":630},
							"force":2100,
							"level":21
						},
					"22":{
							"attrs":{"1":660,"2":660,"3":660},
							"force":2200,
							"level":22
						},
					"23":{
							"attrs":{"1":690,"2":690,"3":690},
							"force":2300,
							"level":23
						},
					"24":{
							"attrs":{"1":720,"2":720,"3":720},
							"force":2400,
							"level":24
						},
					"25":{
							"attrs":{"1":750,"2":750,"3":750},
							"force":2500,
							"level":25
						},
					"26":{
							"attrs":{"1":780,"2":780,"3":780},
							"force":2600,
							"level":26
						},
					"27":{
							"attrs":{"1":810,"2":810,"3":810},
							"force":2700,
							"level":27
						},
					"28":{
							"attrs":{"1":840,"2":840,"3":840},
							"force":2800,
							"level":28
						},
					"29":{
							"attrs":{"1":870,"2":870,"3":870},
							"force":2900,
							"level":29
						},
					"30":{
							"attrs":{"1":900,"2":900,"3":900},
							"force":3000,
							"level":30
						},
					"31":{
							"attrs":{"1":930,"2":930,"3":930},
							"force":3100,
							"level":31
						},
					"32":{
							"attrs":{"1":960,"2":960,"3":960},
							"force":3200,
							"level":32
						},
					"33":{
							"attrs":{"1":990,"2":990,"3":990},
							"force":3300,
							"level":33
						},
					"34":{
							"attrs":{"1":1020,"2":1020,"3":1020},
							"force":3400,
							"level":34
						},
					"35":{
							"attrs":{"1":1050,"2":1050,"3":1050},
							"force":3500,
							"level":35
						},
					"36":{
							"attrs":{"1":1080,"2":1080,"3":1080},
							"force":3600,
							"level":36
						},
					"37":{
							"attrs":{"1":1110,"2":1110,"3":1110},
							"force":3700,
							"level":37
						},
					"38":{
							"attrs":{"1":1140,"2":1140,"3":1140},
							"force":3800,
							"level":38
						},
					"39":{
							"attrs":{"1":1170,"2":1170,"3":1170},
							"force":3900,
							"level":39
						},
					"40":{
							"attrs":{"1":1200,"2":1200,"3":1200},
							"force":4000,
							"level":40
						},
					"41":{
							"attrs":{"1":1230,"2":1230,"3":1230},
							"force":4100,
							"level":41
						},
					"42":{
							"attrs":{"1":1260,"2":1260,"3":1260},
							"force":4200,
							"level":42
						},
					"43":{
							"attrs":{"1":1290,"2":1290,"3":1290},
							"force":4300,
							"level":43
						},
					"44":{
							"attrs":{"1":1320,"2":1320,"3":1320},
							"force":4400,
							"level":44
						},
					"45":{
							"attrs":{"1":1350,"2":1350,"3":1350},
							"force":4500,
							"level":45
						},
					"46":{
							"attrs":{"1":1380,"2":1380,"3":1380},
							"force":4600,
							"level":46
						},
					"47":{
							"attrs":{"1":1410,"2":1410,"3":1410},
							"force":4700,
							"level":47
						},
					"48":{
							"attrs":{"1":1440,"2":1440,"3":1440},
							"force":4800,
							"level":48
						},
					"49":{
							"attrs":{"1":1470,"2":1470,"3":1470},
							"force":4900,
							"level":49
						},
					"50":{
							"attrs":{"1":1500,"2":1500,"3":1500},
							"force":5000,
							"level":50
						}
				},
			"15":{
					"1":{
							"attrs":{"1":500,"2":500,"3":500},
							"force":100,
							"level":1
						},
					"2":{
							"attrs":{"1":1000,"2":1000,"3":1000},
							"force":200,
							"level":2
						},
					"3":{
							"attrs":{"1":1500,"2":1500,"3":1500},
							"force":300,
							"level":3
						},
					"4":{
							"attrs":{"1":2000,"2":2000,"3":2000},
							"force":400,
							"level":4
						},
					"5":{
							"attrs":{"1":2500,"2":2500,"3":2500},
							"force":500,
							"level":5
						},
					"6":{
							"attrs":{"1":3000,"2":3000,"3":3000},
							"force":600,
							"level":6
						},
					"7":{
							"attrs":{"1":3500,"2":3500,"3":3500},
							"force":700,
							"level":7
						},
					"8":{
							"attrs":{"1":4000,"2":4000,"3":4000},
							"force":800,
							"level":8
						},
					"9":{
							"attrs":{"1":4500,"2":4500,"3":4500},
							"force":900,
							"level":9
						},
					"10":{
							"attrs":{"1":5000,"2":5000,"3":5000},
							"force":1000,
							"level":10
						},
					"11":{
							"attrs":{"1":5500,"2":5500,"3":5500},
							"force":1100,
							"level":11
						},
					"12":{
							"attrs":{"1":6000,"2":6000,"3":6000},
							"force":1200,
							"level":12
						},
					"13":{
							"attrs":{"1":6500,"2":6500,"3":6500},
							"force":1300,
							"level":13
						},
					"14":{
							"attrs":{"1":7000,"2":7000,"3":7000},
							"force":1400,
							"level":14
						},
					"15":{
							"attrs":{"1":7500,"2":7500,"3":7500},
							"force":1500,
							"level":15
						},
					"16":{
							"attrs":{"1":8000,"2":8000,"3":8000},
							"force":1600,
							"level":16
						},
					"17":{
							"attrs":{"1":8500,"2":8500,"3":8500},
							"force":1700,
							"level":17
						},
					"18":{
							"attrs":{"1":9000,"2":9000,"3":9000},
							"force":1800,
							"level":18
						},
					"19":{
							"attrs":{"1":9500,"2":9500,"3":9500},
							"force":1900,
							"level":19
						},
					"20":{
							"attrs":{"1":10000,"2":10000,"3":10000},
							"force":2000,
							"level":20
						},
					"21":{
							"attrs":{"1":10500,"2":10500,"3":10500},
							"force":2100,
							"level":21
						},
					"22":{
							"attrs":{"1":11000,"2":11000,"3":11000},
							"force":2200,
							"level":22
						},
					"23":{
							"attrs":{"1":11500,"2":11500,"3":11500},
							"force":2300,
							"level":23
						},
					"24":{
							"attrs":{"1":12000,"2":12000,"3":12000},
							"force":2400,
							"level":24
						},
					"25":{
							"attrs":{"1":12500,"2":12500,"3":12500},
							"force":2500,
							"level":25
						},
					"26":{
							"attrs":{"1":13000,"2":13000,"3":13000},
							"force":2600,
							"level":26
						},
					"27":{
							"attrs":{"1":13500,"2":13500,"3":13500},
							"force":2700,
							"level":27
						},
					"28":{
							"attrs":{"1":14000,"2":14000,"3":14000},
							"force":2800,
							"level":28
						},
					"29":{
							"attrs":{"1":14500,"2":14500,"3":14500},
							"force":2900,
							"level":29
						},
					"30":{
							"attrs":{"1":15000,"2":15000,"3":15000},
							"force":3000,
							"level":30
						},
					"31":{
							"attrs":{"1":15500,"2":15500,"3":15500},
							"force":3100,
							"level":31
						},
					"32":{
							"attrs":{"1":16000,"2":16000,"3":16000},
							"force":3200,
							"level":32
						},
					"33":{
							"attrs":{"1":16500,"2":16500,"3":16500},
							"force":3300,
							"level":33
						},
					"34":{
							"attrs":{"1":17000,"2":17000,"3":17000},
							"force":3400,
							"level":34
						},
					"35":{
							"attrs":{"1":17500,"2":17500,"3":17500},
							"force":3500,
							"level":35
						},
					"36":{
							"attrs":{"1":18000,"2":18000,"3":18000},
							"force":3600,
							"level":36
						},
					"37":{
							"attrs":{"1":18500,"2":18500,"3":18500},
							"force":3700,
							"level":37
						},
					"38":{
							"attrs":{"1":19000,"2":19000,"3":19000},
							"force":3800,
							"level":38
						},
					"39":{
							"attrs":{"1":19500,"2":19500,"3":19500},
							"force":3900,
							"level":39
						},
					"40":{
							"attrs":{"1":20000,"2":20000,"3":20000},
							"force":4000,
							"level":40
						},
					"41":{
							"attrs":{"1":20500,"2":20500,"3":20500},
							"force":4100,
							"level":41
						},
					"42":{
							"attrs":{"1":21000,"2":21000,"3":21000},
							"force":4200,
							"level":42
						},
					"43":{
							"attrs":{"1":21500,"2":21500,"3":21500},
							"force":4300,
							"level":43
						},
					"44":{
							"attrs":{"1":22000,"2":22000,"3":22000},
							"force":4400,
							"level":44
						},
					"45":{
							"attrs":{"1":22500,"2":22500,"3":22500},
							"force":4500,
							"level":45
						},
					"46":{
							"attrs":{"1":23000,"2":23000,"3":23000},
							"force":4600,
							"level":46
						},
					"47":{
							"attrs":{"1":23500,"2":23500,"3":23500},
							"force":4700,
							"level":47
						},
					"48":{
							"attrs":{"1":24000,"2":24000,"3":24000},
							"force":4800,
							"level":48
						},
					"49":{
							"attrs":{"1":24500,"2":24500,"3":24500},
							"force":4900,
							"level":49
						},
					"50":{
							"attrs":{"1":25000,"2":25000,"3":25000},
							"force":5000,
							"level":50
						}
				},
			"16":{
					"1":{
							"attrs":{"1":50,"2":50,"3":50},
							"force":100,
							"level":1
						},
					"2":{
							"attrs":{"1":100,"2":100,"3":100},
							"force":200,
							"level":2
						},
					"3":{
							"attrs":{"1":150,"2":150,"3":150},
							"force":300,
							"level":3
						},
					"4":{
							"attrs":{"1":200,"2":200,"3":200},
							"force":400,
							"level":4
						},
					"5":{
							"attrs":{"1":250,"2":250,"3":250},
							"force":500,
							"level":5
						},
					"6":{
							"attrs":{"1":300,"2":300,"3":300},
							"force":600,
							"level":6
						},
					"7":{
							"attrs":{"1":350,"2":350,"3":350},
							"force":700,
							"level":7
						},
					"8":{
							"attrs":{"1":400,"2":400,"3":400},
							"force":800,
							"level":8
						},
					"9":{
							"attrs":{"1":450,"2":450,"3":450},
							"force":900,
							"level":9
						},
					"10":{
							"attrs":{"1":500,"2":500,"3":500},
							"force":1000,
							"level":10
						},
					"11":{
							"attrs":{"1":550,"2":550,"3":550},
							"force":1100,
							"level":11
						},
					"12":{
							"attrs":{"1":600,"2":600,"3":600},
							"force":1200,
							"level":12
						},
					"13":{
							"attrs":{"1":650,"2":650,"3":650},
							"force":1300,
							"level":13
						},
					"14":{
							"attrs":{"1":700,"2":700,"3":700},
							"force":1400,
							"level":14
						},
					"15":{
							"attrs":{"1":750,"2":750,"3":750},
							"force":1500,
							"level":15
						},
					"16":{
							"attrs":{"1":800,"2":800,"3":800},
							"force":1600,
							"level":16
						},
					"17":{
							"attrs":{"1":850,"2":850,"3":850},
							"force":1700,
							"level":17
						},
					"18":{
							"attrs":{"1":900,"2":900,"3":900},
							"force":1800,
							"level":18
						},
					"19":{
							"attrs":{"1":950,"2":950,"3":950},
							"force":1900,
							"level":19
						},
					"20":{
							"attrs":{"1":1000,"2":1000,"3":1000},
							"force":2000,
							"level":20
						},
					"21":{
							"attrs":{"1":1050,"2":1050,"3":1050},
							"force":2100,
							"level":21
						},
					"22":{
							"attrs":{"1":1100,"2":1100,"3":1100},
							"force":2200,
							"level":22
						},
					"23":{
							"attrs":{"1":1150,"2":1150,"3":1150},
							"force":2300,
							"level":23
						},
					"24":{
							"attrs":{"1":1200,"2":1200,"3":1200},
							"force":2400,
							"level":24
						},
					"25":{
							"attrs":{"1":1250,"2":1250,"3":1250},
							"force":2500,
							"level":25
						},
					"26":{
							"attrs":{"1":1300,"2":1300,"3":1300},
							"force":2600,
							"level":26
						},
					"27":{
							"attrs":{"1":1350,"2":1350,"3":1350},
							"force":2700,
							"level":27
						},
					"28":{
							"attrs":{"1":1400,"2":1400,"3":1400},
							"force":2800,
							"level":28
						},
					"29":{
							"attrs":{"1":1450,"2":1450,"3":1450},
							"force":2900,
							"level":29
						},
					"30":{
							"attrs":{"1":1500,"2":1500,"3":1500},
							"force":3000,
							"level":30
						},
					"31":{
							"attrs":{"1":1550,"2":1550,"3":1550},
							"force":3100,
							"level":31
						},
					"32":{
							"attrs":{"1":1600,"2":1600,"3":1600},
							"force":3200,
							"level":32
						},
					"33":{
							"attrs":{"1":1650,"2":1650,"3":1650},
							"force":3300,
							"level":33
						},
					"34":{
							"attrs":{"1":1700,"2":1700,"3":1700},
							"force":3400,
							"level":34
						},
					"35":{
							"attrs":{"1":1750,"2":1750,"3":1750},
							"force":3500,
							"level":35
						},
					"36":{
							"attrs":{"1":1800,"2":1800,"3":1800},
							"force":3600,
							"level":36
						},
					"37":{
							"attrs":{"1":1850,"2":1850,"3":1850},
							"force":3700,
							"level":37
						},
					"38":{
							"attrs":{"1":1900,"2":1900,"3":1900},
							"force":3800,
							"level":38
						},
					"39":{
							"attrs":{"1":1950,"2":1950,"3":1950},
							"force":3900,
							"level":39
						},
					"40":{
							"attrs":{"1":2000,"2":2000,"3":2000},
							"force":4000,
							"level":40
						},
					"41":{
							"attrs":{"1":2050,"2":2050,"3":2050},
							"force":4100,
							"level":41
						},
					"42":{
							"attrs":{"1":2100,"2":2100,"3":2100},
							"force":4200,
							"level":42
						},
					"43":{
							"attrs":{"1":2150,"2":2150,"3":2150},
							"force":4300,
							"level":43
						},
					"44":{
							"attrs":{"1":2200,"2":2200,"3":2200},
							"force":4400,
							"level":44
						},
					"45":{
							"attrs":{"1":2250,"2":2250,"3":2250},
							"force":4500,
							"level":45
						},
					"46":{
							"attrs":{"1":2300,"2":2300,"3":2300},
							"force":4600,
							"level":46
						},
					"47":{
							"attrs":{"1":2350,"2":2350,"3":2350},
							"force":4700,
							"level":47
						},
					"48":{
							"attrs":{"1":2400,"2":2400,"3":2400},
							"force":4800,
							"level":48
						},
					"49":{
							"attrs":{"1":2450,"2":2450,"3":2450},
							"force":4900,
							"level":49
						},
					"50":{
							"attrs":{"1":2500,"2":2500,"3":2500},
							"force":5000,
							"level":50
						}
				}
		}
}
