{"file":"effect_denglu_xiaohuo.png","frames":{
"effect_denglu_xiaohuo_07":{"x":128,"y":100,"w":64,"h":81,"offX":18,"offY":18,"sourceW":100,"sourceH":100},
"effect_denglu_xiaohuo_08":{"x":66,"y":0,"w":65,"h":87,"offX":17,"offY":13,"sourceW":100,"sourceH":100},
"effect_denglu_xiaohuo_09":{"x":0,"y":0,"w":62,"h":97,"offX":18,"offY":3,"sourceW":100,"sourceH":100},
"effect_denglu_xiaohuo_10":{"x":193,"y":185,"w":59,"h":82,"offX":20,"offY":18,"sourceW":100,"sourceH":100},
"effect_denglu_xiaohuo_11":{"x":128,"y":185,"w":61,"h":82,"offX":22,"offY":18,"sourceW":100,"sourceH":100},
"effect_denglu_xiaohuo_12":{"x":66,"y":91,"w":58,"h":95,"offX":22,"offY":4,"sourceW":100,"sourceH":100},
"effect_denglu_xiaohuo_01":{"x":197,"y":0,"w":55,"h":81,"offX":22,"offY":18,"sourceW":100,"sourceH":100},
"effect_denglu_xiaohuo_02":{"x":0,"y":191,"w":57,"h":83,"offX":22,"offY":16,"sourceW":100,"sourceH":100},
"effect_denglu_xiaohuo_03":{"x":64,"y":190,"w":57,"h":83,"offX":21,"offY":15,"sourceW":100,"sourceH":100},
"effect_denglu_xiaohuo_04":{"x":125,"y":271,"w":59,"h":76,"offX":21,"offY":22,"sourceW":100,"sourceH":100},
"effect_denglu_xiaohuo_05":{"x":0,"y":101,"w":60,"h":86,"offX":22,"offY":13,"sourceW":100,"sourceH":100},
"effect_denglu_xiaohuo_06":{"x":135,"y":0,"w":58,"h":96,"offX":22,"offY":3,"sourceW":100,"sourceH":100}}}