{"file":"effect_yezhantuteng.png","frames":{
"effect_yezhantuteng_09":{"x":0,"y":0,"w":200,"h":222,"offX":0,"offY":0,"sourceW":200,"sourceH":222},
"effect_yezhantuteng_10":{"x":400,"y":441,"w":199,"h":199,"offX":1,"offY":23,"sourceW":200,"sourceH":222},
"effect_yezhantuteng_11":{"x":201,"y":226,"w":200,"h":204,"offX":0,"offY":18,"sourceW":200,"sourceH":222},
"effect_yezhantuteng_12":{"x":201,"y":434,"w":195,"h":208,"offX":3,"offY":14,"sourceW":200,"sourceH":222},
"effect_yezhantuteng_01":{"x":609,"y":225,"w":194,"h":215,"offX":4,"offY":7,"sourceW":200,"sourceH":222},
"effect_yezhantuteng_02":{"x":609,"y":0,"w":195,"h":221,"offX":4,"offY":1,"sourceW":200,"sourceH":222},
"effect_yezhantuteng_03":{"x":808,"y":0,"w":198,"h":217,"offX":2,"offY":5,"sourceW":200,"sourceH":222},
"effect_yezhantuteng_04":{"x":808,"y":221,"w":195,"h":220,"offX":4,"offY":2,"sourceW":200,"sourceH":222},
"effect_yezhantuteng_05":{"x":0,"y":226,"w":197,"h":211,"offX":3,"offY":11,"sourceW":200,"sourceH":222},
"effect_yezhantuteng_06":{"x":407,"y":222,"w":198,"h":215,"offX":2,"offY":7,"sourceW":200,"sourceH":222},
"effect_yezhantuteng_07":{"x":407,"y":0,"w":198,"h":218,"offX":2,"offY":4,"sourceW":200,"sourceH":222},
"effect_yezhantuteng_08":{"x":204,"y":0,"w":199,"h":222,"offX":1,"offY":0,"sourceW":200,"sourceH":222}}}