{"file":"effect_xunbao_baoxiangtexiao.png","frames":{
"effect_xunbao_1_02":{"x":516,"y":0,"w":512,"h":463,"offX":0,"offY":4,"sourceW":512,"sourceH":512},
"effect_xunbao_1_03":{"x":1032,"y":0,"w":477,"h":404,"offX":13,"offY":32,"sourceW":512,"sourceH":512},
"effect_xunbao_1_04":{"x":1032,"y":408,"w":470,"h":334,"offX":15,"offY":79,"sourceW":512,"sourceH":512},
"effect_xunbao_1_05":{"x":1513,"y":353,"w":512,"h":329,"offX":0,"offY":84,"sourceW":512,"sourceH":512},
"effect_xunbao_1_06":{"x":1513,"y":0,"w":512,"h":349,"offX":0,"offY":64,"sourceW":512,"sourceH":512},
"effect_xunbao_1_07":{"x":516,"y":467,"w":300,"h":291,"offX":92,"offY":122,"sourceW":512,"sourceH":512},
"effect_xunbao_1_01":{"x":0,"y":0,"w":512,"h":470,"offX":0,"offY":2,"sourceW":512,"sourceH":512}}}