{"file":"skill_fs_huoqiu_4_l.png","frames":{
"skill_fs_huoqiu_4_l_06":{"x":206,"y":384,"w":206,"h":128,"offX":1,"offY":0,"sourceW":211,"sourceH":129},
"skill_fs_huoqiu_4_l_07":{"x":206,"y":256,"w":206,"h":128,"offX":1,"offY":0,"sourceW":211,"sourceH":129},
"skill_fs_huoqiu_4_l_08":{"x":0,"y":384,"w":206,"h":128,"offX":0,"offY":0,"sourceW":211,"sourceH":129},
"skill_fs_huoqiu_4_l_01":{"x":0,"y":256,"w":206,"h":128,"offX":5,"offY":1,"sourceW":211,"sourceH":129},
"skill_fs_huoqiu_4_l_02":{"x":206,"y":128,"w":206,"h":128,"offX":3,"offY":1,"sourceW":211,"sourceH":129},
"skill_fs_huoqiu_4_l_03":{"x":0,"y":128,"w":206,"h":128,"offX":2,"offY":0,"sourceW":211,"sourceH":129},
"skill_fs_huoqiu_4_l_04":{"x":206,"y":0,"w":206,"h":128,"offX":1,"offY":0,"sourceW":211,"sourceH":129},
"skill_fs_huoqiu_4_l_05":{"x":0,"y":0,"w":206,"h":128,"offX":0,"offY":1,"sourceW":211,"sourceH":129}}}