{"file":"skill_fashi_huoqiang_4_b.png","frames":{
"skill_fashi_huoqiang_4_b_09":{"x":164,"y":401,"w":83,"h":103,"offX":358,"offY":226,"sourceW":800,"sourceH":600},
"skill_fashi_huoqiang_4_b_10":{"x":170,"y":0,"w":85,"h":109,"offX":359,"offY":220,"sourceW":800,"sourceH":600},
"skill_fashi_huoqiang_4_b_01":{"x":82,"y":401,"w":82,"h":109,"offX":360,"offY":220,"sourceW":800,"sourceH":600},
"skill_fashi_huoqiang_4_b_02":{"x":83,"y":156,"w":88,"h":109,"offX":359,"offY":220,"sourceW":800,"sourceH":600},
"skill_fashi_huoqiang_4_b_03":{"x":87,"y":0,"w":83,"h":109,"offX":357,"offY":220,"sourceW":800,"sourceH":600},
"skill_fashi_huoqiang_4_b_04":{"x":171,"y":109,"w":84,"h":108,"offX":359,"offY":221,"sourceW":800,"sourceH":600},
"skill_fashi_huoqiang_4_b_05":{"x":82,"y":292,"w":88,"h":109,"offX":357,"offY":220,"sourceW":800,"sourceH":600},
"skill_fashi_huoqiang_4_b_06":{"x":0,"y":0,"w":87,"h":156,"offX":358,"offY":173,"sourceW":800,"sourceH":600},
"skill_fashi_huoqiang_4_b_07":{"x":0,"y":156,"w":83,"h":136,"offX":357,"offY":193,"sourceW":800,"sourceH":600},
"skill_fashi_huoqiang_4_b_08":{"x":0,"y":292,"w":82,"h":136,"offX":358,"offY":193,"sourceW":800,"sourceH":600}}}