{"file":"skill_zs_liehuo_l.png","frames":{
"skill_zs_liehuo_l_35":{"x":906,"y":1699,"w":80,"h":242,"offX":702,"offY":671,"sourceW":1500,"sourceH":1500},
"skill_zs_liehuo_l_01":{"x":756,"y":1332,"w":171,"h":173,"offX":764,"offY":652,"sourceW":1500,"sourceH":1500},
"skill_zs_liehuo_l_02":{"x":927,"y":1332,"w":69,"h":225,"offX":750,"offY":577,"sourceW":1500,"sourceH":1500},
"skill_zs_liehuo_l_03":{"x":0,"y":1406,"w":173,"h":433,"offX":675,"offY":452,"sourceW":1500,"sourceH":1500},
"skill_zs_liehuo_l_04":{"x":173,"y":1406,"w":202,"h":370,"offX":633,"offY":488,"sourceW":1500,"sourceH":1500},
"skill_zs_liehuo_l_05":{"x":430,"y":814,"w":202,"h":354,"offX":629,"offY":507,"sourceW":1500,"sourceH":1500},
"skill_zs_liehuo_l_06":{"x":892,"y":677,"w":132,"h":297,"offX":694,"offY":504,"sourceW":1500,"sourceH":1500},
"skill_zs_liehuo_l_07":{"x":634,"y":1589,"w":98,"h":298,"offX":696,"offY":502,"sourceW":1500,"sourceH":1500},
"skill_zs_liehuo_l_08":{"x":766,"y":974,"w":166,"h":209,"offX":609,"offY":566,"sourceW":1500,"sourceH":1500},
"skill_zs_liehuo_l_09":{"x":756,"y":1505,"w":137,"h":194,"offX":682,"offY":573,"sourceW":1500,"sourceH":1500},
"skill_zs_liehuo_l_10":{"x":375,"y":1369,"w":256,"h":262,"offX":667,"offY":537,"sourceW":1500,"sourceH":1500},
"skill_zs_liehuo_l_11":{"x":373,"y":271,"w":252,"h":293,"offX":690,"offY":490,"sourceW":1500,"sourceH":1500},
"skill_zs_liehuo_l_12":{"x":0,"y":0,"w":297,"h":433,"offX":689,"offY":476,"sourceW":1500,"sourceH":1500},
"skill_zs_liehuo_l_13":{"x":375,"y":1631,"w":259,"h":242,"offX":707,"offY":534,"sourceW":1500,"sourceH":1500},
"skill_zs_liehuo_l_14":{"x":625,"y":271,"w":251,"h":243,"offX":710,"offY":531,"sourceW":1500,"sourceH":1500},
"skill_zs_liehuo_l_15":{"x":664,"y":514,"w":228,"h":209,"offX":667,"offY":536,"sourceW":1500,"sourceH":1500},
"skill_zs_liehuo_l_16":{"x":766,"y":1183,"w":218,"h":149,"offX":679,"offY":601,"sourceW":1500,"sourceH":1500},
"skill_zs_liehuo_l_17":{"x":0,"y":951,"w":430,"h":210,"offX":615,"offY":608,"sourceW":1500,"sourceH":1500},
"skill_zs_liehuo_l_18":{"x":0,"y":695,"w":367,"h":256,"offX":669,"offY":552,"sourceW":1500,"sourceH":1500},
"skill_zs_liehuo_l_19":{"x":0,"y":433,"w":373,"h":262,"offX":683,"offY":546,"sourceW":1500,"sourceH":1500},
"skill_zs_liehuo_l_20":{"x":324,"y":1168,"w":334,"h":201,"offX":703,"offY":606,"sourceW":1500,"sourceH":1500},
"skill_zs_liehuo_l_21":{"x":0,"y":1839,"w":338,"h":157,"offX":701,"offY":653,"sourceW":1500,"sourceH":1500},
"skill_zs_liehuo_l_22":{"x":664,"y":723,"w":179,"h":225,"offX":684,"offY":486,"sourceW":1500,"sourceH":1500},
"skill_zs_liehuo_l_23":{"x":631,"y":1940,"w":168,"h":102,"offX":689,"offY":634,"sourceW":1500,"sourceH":1500},
"skill_zs_liehuo_l_24":{"x":297,"y":0,"w":372,"h":271,"offX":619,"offY":625,"sourceW":1500,"sourceH":1500},
"skill_zs_liehuo_l_25":{"x":0,"y":1161,"w":324,"h":245,"offX":677,"offY":638,"sourceW":1500,"sourceH":1500},
"skill_zs_liehuo_l_26":{"x":669,"y":0,"w":309,"h":262,"offX":704,"offY":638,"sourceW":1500,"sourceH":1500},
"skill_zs_liehuo_l_27":{"x":373,"y":564,"w":291,"h":250,"offX":726,"offY":643,"sourceW":1500,"sourceH":1500},
"skill_zs_liehuo_l_28":{"x":338,"y":1873,"w":293,"h":147,"offX":726,"offY":742,"sourceW":1500,"sourceH":1500},
"skill_zs_liehuo_l_29":{"x":831,"y":1699,"w":75,"h":308,"offX":670,"offY":515,"sourceW":1500,"sourceH":1500},
"skill_zs_liehuo_l_30":{"x":367,"y":814,"w":63,"h":131,"offX":683,"offY":654,"sourceW":1500,"sourceH":1500},
"skill_zs_liehuo_l_31":{"x":892,"y":262,"w":111,"h":415,"offX":683,"offY":588,"sourceW":1500,"sourceH":1500},
"skill_zs_liehuo_l_32":{"x":658,"y":948,"w":108,"h":339,"offX":687,"offY":623,"sourceW":1500,"sourceH":1500},
"skill_zs_liehuo_l_33":{"x":658,"y":1287,"w":98,"h":302,"offX":692,"offY":638,"sourceW":1500,"sourceH":1500},
"skill_zs_liehuo_l_34":{"x":732,"y":1699,"w":99,"h":241,"offX":694,"offY":685,"sourceW":1500,"sourceH":1500}}}