{"file":"skill_bing_buff.png","frames":{
"skill_bing_buff_06":{"x":588,"y":456,"w":588,"h":444,"offX":9,"offY":141,"sourceW":600,"sourceH":600},
"skill_bing_buff_01":{"x":0,"y":468,"w":588,"h":441,"offX":9,"offY":144,"sourceW":600,"sourceH":600},
"skill_bing_buff_02":{"x":1176,"y":450,"w":588,"h":450,"offX":9,"offY":135,"sourceW":600,"sourceH":600},
"skill_bing_buff_03":{"x":588,"y":0,"w":588,"h":456,"offX":9,"offY":129,"sourceW":600,"sourceH":600},
"skill_bing_buff_04":{"x":0,"y":0,"w":588,"h":468,"offX":9,"offY":117,"sourceW":600,"sourceH":600},
"skill_bing_buff_05":{"x":1176,"y":0,"w":588,"h":450,"offX":9,"offY":135,"sourceW":600,"sourceH":600}}}